{
  "country": {
    "slug": "ethiopia",
    "name": "Ethiopia"
  },
  "generatedAt": "2026-07-21T16:19:11.574Z",
  "users": [
    {
      "rank": 1,
      "username": "mohammedsbd",
      "realname": "Mohammed Salih",
      "profile": "https://github.com/mohammedsbd",
      "commits": 8232,
      "avatar": "https://avatars.githubusercontent.com/u/175719241?u=bd73924efc3d4b75148eb4c1d7e0bf565fcfbaf1&v=4&s=40"
    },
    {
      "rank": 2,
      "username": "poricf",
      "realname": "Fahmi Dinsefa",
      "profile": "https://github.com/poricf",
      "commits": 4366,
      "avatar": "https://avatars.githubusercontent.com/u/116361774?u=f403a256f4098fc380dd42cfa0160067dcd44109&v=4&s=40"
    },
    {
      "rank": 3,
      "username": "anon381",
      "realname": "Yabets Maregn",
      "profile": "https://github.com/anon381",
      "commits": 3418,
      "avatar": "https://avatars.githubusercontent.com/u/149154528?u=71bb82af414dcab1b484615def6e7abf5bf5757a&v=4&s=40"
    },
    {
      "rank": 4,
      "username": "dawitlabs",
      "realname": "Dawit Worku",
      "profile": "https://github.com/dawitlabs",
      "commits": 2834,
      "avatar": "https://avatars.githubusercontent.com/u/144016968?u=cdffb2a467f040c89e949f8a567ef80428519c0f&v=4&s=40"
    },
    {
      "rank": 5,
      "username": "FiraBro",
      "realname": "Firagos Jemal",
      "profile": "https://github.com/FiraBro",
      "commits": 2385,
      "avatar": "https://avatars.githubusercontent.com/u/192071818?u=2b1a32e418b5c6d8396f9ed5c72d0c4690a04cfa&v=4&s=40"
    },
    {
      "rank": 6,
      "username": "game-ale",
      "realname": "Gemechu Alemu Bedasa",
      "profile": "https://github.com/game-ale",
      "commits": 2247,
      "avatar": "https://avatars.githubusercontent.com/u/186712687?u=0f074e0c16620246ac339dde36cd4af8cf94fe78&v=4&s=40"
    },
    {
      "rank": 7,
      "username": "nahom-zewdu",
      "realname": "Nahom Zewdu",
      "profile": "https://github.com/nahom-zewdu",
      "commits": 2105,
      "avatar": "https://avatars.githubusercontent.com/u/116443749?u=20eb2323ce8803fdf5186d171dc9b4b45c38e15f&v=4&s=40"
    },
    {
      "rank": 8,
      "username": "tekluabayneh",
      "realname": "Teklu Abayneh",
      "profile": "https://github.com/tekluabayneh",
      "commits": 2049,
      "avatar": "https://avatars.githubusercontent.com/u/160180978?u=f2c19a13216d155839e6e2ee8a1941e7a2d427c8&v=4&s=40"
    },
    {
      "rank": 9,
      "username": "ami798",
      "realname": "Amira Abdurahman",
      "profile": "https://github.com/ami798",
      "commits": 1779,
      "avatar": "https://avatars.githubusercontent.com/u/183639755?u=160459985baa2abcc208049adb81629a9c82fb7e&v=4&s=40"
    },
    {
      "rank": 10,
      "username": "Peterase-1",
      "realname": "Petros Asegid",
      "profile": "https://github.com/Peterase-1",
      "commits": 1774,
      "avatar": "https://avatars.githubusercontent.com/u/177719527?u=cf398b23c65b7c5c21cfc6ecedb9753639b79b7f&v=4&s=40"
    },
    {
      "rank": 11,
      "username": "Mekdi-kassa",
      "realname": "Mekdelawit Abadina",
      "profile": "https://github.com/Mekdi-kassa",
      "commits": 1762,
      "avatar": "https://avatars.githubusercontent.com/u/178584740?u=a952be34aa62e79f65ade5196dd02297639e1da6&v=4&s=40"
    },
    {
      "rank": 12,
      "username": "Maxd646",
      "realname": "Daniel Kebede",
      "profile": "https://github.com/Maxd646",
      "commits": 1689,
      "avatar": "https://avatars.githubusercontent.com/u/184818393?u=91775c0d5a600bd01117dae1a57bb89720affeed&v=4&s=40"
    },
    {
      "rank": 13,
      "username": "betselotT",
      "realname": "Betselot Tesfa",
      "profile": "https://github.com/betselotT",
      "commits": 1639,
      "avatar": "https://avatars.githubusercontent.com/u/99252072?u=4606b5c63af952d37598aafaf11162041b68f719&v=4&s=40"
    },
    {
      "rank": 14,
      "username": "frectonz",
      "realname": "Fraol Lemecha",
      "profile": "https://github.com/frectonz",
      "commits": 1599,
      "avatar": "https://avatars.githubusercontent.com/u/53809656?u=83268faafff1ed0c8c36211717f2f711c93f9bdc&v=4&s=40"
    },
    {
      "rank": 15,
      "username": "eyobbegashaw",
      "realname": "Eyob Begashaw Ayele",
      "profile": "https://github.com/eyobbegashaw",
      "commits": 1480,
      "avatar": "https://avatars.githubusercontent.com/u/188770920?u=0fd2bd6d1c702f9d98acaf4b1678d368b0e29256&v=4&s=40"
    },
    {
      "rank": 16,
      "username": "gemachistesfaye",
      "realname": "Gemachis Tesfaye",
      "profile": "https://github.com/gemachistesfaye",
      "commits": 1464,
      "avatar": "https://avatars.githubusercontent.com/u/196615697?u=c55f9453fee5ca19115d11d6a1eb434e4169071e&v=4&s=40"
    },
    {
      "rank": 17,
      "username": "Hailemeskel-Getaneh",
      "realname": "Hailemeskel Getaneh",
      "profile": "https://github.com/Hailemeskel-Getaneh",
      "commits": 1432,
      "avatar": "https://avatars.githubusercontent.com/u/159171440?u=6cc13cc10038f21d4d1147793e845cee8acfb643&v=4&s=40"
    },
    {
      "rank": 18,
      "username": "milkias17",
      "realname": "Milkias Yeheyis",
      "profile": "https://github.com/milkias17",
      "commits": 1411,
      "avatar": "https://avatars.githubusercontent.com/u/66522725?u=e30dbc0d22e2d47027507306ed7d52990e49dd53&v=4&s=40"
    },
    {
      "rank": 19,
      "username": "letera1",
      "realname": "Letera Tujo",
      "profile": "https://github.com/letera1",
      "commits": 1381,
      "avatar": "https://avatars.githubusercontent.com/u/168364436?u=1251a6215d90f2933f9be50a4db6c3adc1c2d684&v=4&s=40"
    },
    {
      "rank": 20,
      "username": "esti08-hu",
      "realname": "Estifanos A.",
      "profile": "https://github.com/esti08-hu",
      "commits": 1343,
      "avatar": "https://avatars.githubusercontent.com/u/98952769?u=a72b5000449c5f4c5807cdb11ceb41133d9e3568&v=4&s=40"
    },
    {
      "rank": 21,
      "username": "Tewodros-Tilahun-01",
      "realname": "tewodros tilahun",
      "profile": "https://github.com/Tewodros-Tilahun-01",
      "commits": 1343,
      "avatar": "https://avatars.githubusercontent.com/u/113050664?v=4&s=40"
    },
    {
      "rank": 22,
      "username": "Leta-Kasahun",
      "realname": "🌟 **Leta  Kasahun**",
      "profile": "https://github.com/Leta-Kasahun",
      "commits": 1309,
      "avatar": "https://avatars.githubusercontent.com/u/193022391?u=892dff5a10d05892a027760a1a9ddab82a3888bb&v=4&s=40"
    },
    {
      "rank": 23,
      "username": "BemnetMussa",
      "realname": "Bemnet Mussa",
      "profile": "https://github.com/BemnetMussa",
      "commits": 1250,
      "avatar": "https://avatars.githubusercontent.com/u/117770007?u=296728c04a37b1165865777046ebc7668e0d34c4&v=4&s=40"
    },
    {
      "rank": 24,
      "username": "dawit2123",
      "realname": "Dawit Munie",
      "profile": "https://github.com/dawit2123",
      "commits": 1248,
      "avatar": "https://avatars.githubusercontent.com/u/106137900?u=fb1d6baa2709d44afa604eb205bf38168f21b804&v=4&s=40"
    },
    {
      "rank": 25,
      "username": "samayine",
      "realname": "Samuel Ayine",
      "profile": "https://github.com/samayine",
      "commits": 1235,
      "avatar": "https://avatars.githubusercontent.com/u/105039572?u=52863f63dd61f8e3204ace64fd5836436fb3ad98&v=4&s=40"
    },
    {
      "rank": 26,
      "username": "Shambel96",
      "realname": "Shambel Dechu",
      "profile": "https://github.com/Shambel96",
      "commits": 1223,
      "avatar": "https://avatars.githubusercontent.com/u/172547097?u=79f1f9af67966f39175eff051dd832d69539f9ac&v=4&s=40"
    },
    {
      "rank": 27,
      "username": "Chala751",
      "realname": "Chala Temesgen",
      "profile": "https://github.com/Chala751",
      "commits": 1206,
      "avatar": "https://avatars.githubusercontent.com/u/174883759?u=b67db6c664d114896dc889bc585b9a199e94a5c8&v=4&s=40"
    },
    {
      "rank": 28,
      "username": "birhanumoges",
      "realname": "Birhanumoges",
      "profile": "https://github.com/birhanumoges",
      "commits": 1175,
      "avatar": "https://avatars.githubusercontent.com/u/211559761?u=f0f63eedd999468dbf86c2ac1c43203eb73cf42e&v=4&s=40"
    },
    {
      "rank": 29,
      "username": "segnig",
      "realname": "Segni Girma",
      "profile": "https://github.com/segnig",
      "commits": 1162,
      "avatar": "https://avatars.githubusercontent.com/u/106369427?v=4&s=40"
    },
    {
      "rank": 30,
      "username": "BytePhilosopher",
      "realname": "Yostina Abera Gobie",
      "profile": "https://github.com/BytePhilosopher",
      "commits": 1155,
      "avatar": "https://avatars.githubusercontent.com/u/204242121?u=9a8304a2032d6d55774ea0c5b596d71f2d089a03&v=4&s=40"
    },
    {
      "rank": 31,
      "username": "zacktam12",
      "realname": "Zekarias Tamiru",
      "profile": "https://github.com/zacktam12",
      "commits": 1136,
      "avatar": "https://avatars.githubusercontent.com/u/152074229?u=ff7e9681c8cf0dc10f5018173a31140dea101e20&v=4&s=40"
    },
    {
      "rank": 32,
      "username": "Eyob-smax",
      "realname": "Eyob Simachew",
      "profile": "https://github.com/Eyob-smax",
      "commits": 1104,
      "avatar": "https://avatars.githubusercontent.com/u/167653682?u=601c5382f10eeb0209b645b501f27bb37758f065&v=4&s=40"
    },
    {
      "rank": 33,
      "username": "Atnatewoss",
      "realname": "Atnatewos",
      "profile": "https://github.com/Atnatewoss",
      "commits": 1083,
      "avatar": "https://avatars.githubusercontent.com/u/165107377?u=559dadb7b8af4f3b84abc45cbfd6853ec3afe4f9&v=4&s=40"
    },
    {
      "rank": 34,
      "username": "ayanasamuel8",
      "realname": "Ayana Samuel",
      "profile": "https://github.com/ayanasamuel8",
      "commits": 1057,
      "avatar": "https://avatars.githubusercontent.com/u/125457325?u=ac0ba20865bee1d5685781007c76318e38222172&v=4&s=40"
    },
    {
      "rank": 35,
      "username": "annah11",
      "realname": "Hana Mesfin",
      "profile": "https://github.com/annah11",
      "commits": 1032,
      "avatar": "https://avatars.githubusercontent.com/u/137293765?u=49f118198e88d9c7341f2b6d92f4eafbd79f264d&v=4&s=40"
    },
    {
      "rank": 36,
      "username": "hawire",
      "realname": "Bitania Finoteselam",
      "profile": "https://github.com/hawire",
      "commits": 1019,
      "avatar": "https://avatars.githubusercontent.com/u/205974689?u=1c9e4568e109cc2ec7fa39d2ed17eb0578a1b873&v=4&s=40"
    },
    {
      "rank": 37,
      "username": "YosephSE",
      "realname": "Yoseph Kedir",
      "profile": "https://github.com/YosephSE",
      "commits": 992,
      "avatar": "https://avatars.githubusercontent.com/u/88291669?u=3f148e45819288aa4d2d0036c54ff6cbb65b1acc&v=4&s=40"
    },
    {
      "rank": 38,
      "username": "Itsyabitaa",
      "realname": "Yeabsira Endale Bekele",
      "profile": "https://github.com/Itsyabitaa",
      "commits": 991,
      "avatar": "https://avatars.githubusercontent.com/u/125443630?u=fd2daf6ef29ffa7c12970c75a6a33ce86e2c05b0&v=4&s=40"
    },
    {
      "rank": 39,
      "username": "esmaelmohammed-ux",
      "realname": "Esmael",
      "profile": "https://github.com/esmaelmohammed-ux",
      "commits": 983,
      "avatar": "https://avatars.githubusercontent.com/u/237391690?u=5d563510d0c1ca306de2b5f894c87d0be01791fb&v=4&s=40"
    },
    {
      "rank": 40,
      "username": "dagimg-dot",
      "realname": "Dagim G. Astatkie",
      "profile": "https://github.com/dagimg-dot",
      "commits": 959,
      "avatar": "https://avatars.githubusercontent.com/u/106905365?u=6615e5805c166c4390e3f19adeb157bcf568873f&v=4&s=40"
    },
    {
      "rank": 41,
      "username": "yaredtsy",
      "realname": "yared tsegaye",
      "profile": "https://github.com/yaredtsy",
      "commits": 936,
      "avatar": "https://avatars.githubusercontent.com/u/34584266?v=4&s=40"
    },
    {
      "rank": 42,
      "username": "Mikearaya",
      "realname": "Mikael Araya",
      "profile": "https://github.com/Mikearaya",
      "commits": 928,
      "avatar": "https://avatars.githubusercontent.com/u/9751246?u=32efa8d9e5554708887d3b8a2fd210fd266e8133&v=4&s=40"
    },
    {
      "rank": 43,
      "username": "getabalewKemaw",
      "realname": "Getabalew Kemaw",
      "profile": "https://github.com/getabalewKemaw",
      "commits": 924,
      "avatar": "https://avatars.githubusercontent.com/u/192819343?u=5fbee44f690db03010b176a9082957051bde7ffd&v=4&s=40"
    },
    {
      "rank": 44,
      "username": "Kumneger0",
      "realname": "kumneger Wondimu",
      "profile": "https://github.com/Kumneger0",
      "commits": 915,
      "avatar": "https://avatars.githubusercontent.com/u/93655689?u=f8050490b11f767d53d48c467f68ee2ae6fdb255&v=4&s=40"
    },
    {
      "rank": 45,
      "username": "gosag",
      "realname": "Gosa Girma Ejersa",
      "profile": "https://github.com/gosag",
      "commits": 895,
      "avatar": "https://avatars.githubusercontent.com/u/206127554?u=622f63dd7c72f8881b9da97f5aac26d399761707&v=4&s=40"
    },
    {
      "rank": 46,
      "username": "J0na555",
      "realname": "Yonas",
      "profile": "https://github.com/J0na555",
      "commits": 875,
      "avatar": "https://avatars.githubusercontent.com/u/196735486?u=d4ba087000a4e0e55110298d42d836de258ac5b8&v=4&s=40"
    },
    {
      "rank": 47,
      "username": "Kidtd12",
      "realname": "kidist tadesse",
      "profile": "https://github.com/Kidtd12",
      "commits": 867,
      "avatar": "https://avatars.githubusercontent.com/u/187760549?u=efd57662fe7cdf2803e672cc4c1b9b2208d65f02&v=4&s=40"
    },
    {
      "rank": 48,
      "username": "MelakuDemeke",
      "realname": "Melaku Demeke",
      "profile": "https://github.com/MelakuDemeke",
      "commits": 857,
      "avatar": "https://avatars.githubusercontent.com/u/38818398?u=2a84ffcfea33f92b313930fed7905d3974d24a69&v=4&s=40"
    },
    {
      "rank": 49,
      "username": "halleygz",
      "realname": "Halleluya Mulugeta",
      "profile": "https://github.com/halleygz",
      "commits": 851,
      "avatar": "https://avatars.githubusercontent.com/u/98106633?u=3cfe8455093e6a8984517bc87c81bd49aca365f6&v=4&s=40"
    },
    {
      "rank": 50,
      "username": "TadesseAsrie",
      "realname": "Tadesse Asrie",
      "profile": "https://github.com/TadesseAsrie",
      "commits": 847,
      "avatar": "https://avatars.githubusercontent.com/u/223765537?u=626170ef8d167b31e915c917a50ecd11205c6f71&v=4&s=40"
    },
    {
      "rank": 51,
      "username": "jabezinu",
      "realname": "Yab",
      "profile": "https://github.com/jabezinu",
      "commits": 846,
      "avatar": "https://avatars.githubusercontent.com/u/189609981?u=9b6863b57c94ff7eb09cc00a419b80ac5f6bcefd&v=4&s=40"
    },
    {
      "rank": 52,
      "username": "tenbite-daniel",
      "realname": "Tenbite Daniel",
      "profile": "https://github.com/tenbite-daniel",
      "commits": 839,
      "avatar": "https://avatars.githubusercontent.com/u/101597746?v=4&s=40"
    },
    {
      "rank": 53,
      "username": "ake144",
      "realname": "Aklilu Tamirat",
      "profile": "https://github.com/ake144",
      "commits": 830,
      "avatar": "https://avatars.githubusercontent.com/u/122739445?u=75e2479ad1102c2e7274dcffa5ae711a26eec5ce&v=4&s=40"
    },
    {
      "rank": 54,
      "username": "Million-art",
      "realname": "million",
      "profile": "https://github.com/Million-art",
      "commits": 821,
      "avatar": "https://avatars.githubusercontent.com/u/74927604?u=2bdb0bc4a2d3e7d708f850983ca4adcecdea793b&v=4&s=40"
    },
    {
      "rank": 55,
      "username": "Samuel-0228",
      "realname": "Samuel",
      "profile": "https://github.com/Samuel-0228",
      "commits": 820,
      "avatar": "https://avatars.githubusercontent.com/u/198710196?u=f07e186b540db8e2626e0abf99e05f5bc3243f96&v=4&s=40"
    },
    {
      "rank": 56,
      "username": "mntc3434",
      "realname": "Mintesinot getu",
      "profile": "https://github.com/mntc3434",
      "commits": 811,
      "avatar": "https://avatars.githubusercontent.com/u/148215622?u=91021e467b23399e0e9ea96bef489a203db8c935&v=4&s=40"
    },
    {
      "rank": 57,
      "username": "amdebirhan-asmamaw",
      "realname": "Amdebirhan Asmamaw",
      "profile": "https://github.com/amdebirhan-asmamaw",
      "commits": 808,
      "avatar": "https://avatars.githubusercontent.com/u/131457486?u=99ed854ae679c53d69979290c7a6ca201db857a6&v=4&s=40"
    },
    {
      "rank": 58,
      "username": "Benawi",
      "realname": "Habtamu (ቤናዊ",
      "profile": "https://github.com/Benawi",
      "commits": 791,
      "avatar": "https://avatars.githubusercontent.com/u/21217148?u=292933e6f3465781f0d52b86f5c4d0a67daad07b&v=4&s=40"
    },
    {
      "rank": 59,
      "username": "devabdisa",
      "realname": "Abdisa ketema",
      "profile": "https://github.com/devabdisa",
      "commits": 786,
      "avatar": "https://avatars.githubusercontent.com/u/193072882?u=5cda4516a477df86112d2877baa9da88b23d2a49&v=4&s=40"
    },
    {
      "rank": 60,
      "username": "addanex",
      "realname": "Yosef A.",
      "profile": "https://github.com/addanex",
      "commits": 760,
      "avatar": "https://avatars.githubusercontent.com/u/125744573?u=5f64e13cca377839c9cbeaf05f0fd93c361750d9&v=4&s=40"
    },
    {
      "rank": 61,
      "username": "AbdulazizAyalew",
      "realname": "Abdulaziz Ayalew",
      "profile": "https://github.com/AbdulazizAyalew",
      "commits": 760,
      "avatar": "https://avatars.githubusercontent.com/u/162428984?u=63a54645f12340654f17d830079b5b72927df0ae&v=4&s=40"
    },
    {
      "rank": 62,
      "username": "Bini-2002",
      "realname": "Biniyam Getachew",
      "profile": "https://github.com/Bini-2002",
      "commits": 758,
      "avatar": "https://avatars.githubusercontent.com/u/133484929?u=c35161c0e232a80cf0c9624801009d15b60f7db1&v=4&s=40"
    },
    {
      "rank": 63,
      "username": "yeab-B",
      "realname": "Yeabsira Behailu",
      "profile": "https://github.com/yeab-B",
      "commits": 740,
      "avatar": "https://avatars.githubusercontent.com/u/166545362?u=2784b3aac4c895b1581a5b0543e8e9da040bc753&v=4&s=40"
    },
    {
      "rank": 64,
      "username": "Tesfamichael12",
      "realname": "Tesfamichael Tafere",
      "profile": "https://github.com/Tesfamichael12",
      "commits": 737,
      "avatar": "https://avatars.githubusercontent.com/u/149233683?u=ca6d73466da6d33a38a41d01c45009d871fb6f64&v=4&s=40"
    },
    {
      "rank": 65,
      "username": "Fitsumhelina",
      "realname": "Fitsum Helina",
      "profile": "https://github.com/Fitsumhelina",
      "commits": 736,
      "avatar": "https://avatars.githubusercontent.com/u/151903384?u=42e8344a86d24e85c062c8d251cc96181eedf4ec&v=4&s=40"
    },
    {
      "rank": 66,
      "username": "ZorEl212",
      "realname": "Yeabsira Desalegn",
      "profile": "https://github.com/ZorEl212",
      "commits": 735,
      "avatar": "https://avatars.githubusercontent.com/u/93014559?u=7fd465beeb33c049a060c9af3b497948d995fe66&v=4&s=40"
    },
    {
      "rank": 67,
      "username": "jossephus",
      "realname": "Josseph",
      "profile": "https://github.com/jossephus",
      "commits": 730,
      "avatar": "https://avatars.githubusercontent.com/u/46337696?u=27e02efb31ff2ff3b49dcf2fb7116b2079651dea&v=4&s=40"
    },
    {
      "rank": 68,
      "username": "sebrinamusbah",
      "realname": "sebrin",
      "profile": "https://github.com/sebrinamusbah",
      "commits": 718,
      "avatar": "https://avatars.githubusercontent.com/u/203940429?u=7f07430a49ee11578eb23b9a9a6061d6a925a567&v=4&s=40"
    },
    {
      "rank": 69,
      "username": "hababisha",
      "realname": "Haileamlak",
      "profile": "https://github.com/hababisha",
      "commits": 702,
      "avatar": "https://avatars.githubusercontent.com/u/182012569?u=7c2cc8dd0a2a520db0d3156f2750c2244ca497b6&v=4&s=40"
    },
    {
      "rank": 70,
      "username": "Tsedniya",
      "realname": "Tsedniya Frezewed",
      "profile": "https://github.com/Tsedniya",
      "commits": 698,
      "avatar": "https://avatars.githubusercontent.com/u/136121375?u=631f724a870885553a1898774e32ee15a24ced81&v=4&s=40"
    },
    {
      "rank": 71,
      "username": "Neftalem-Dagnachew",
      "realname": "Neftalem",
      "profile": "https://github.com/Neftalem-Dagnachew",
      "commits": 694,
      "avatar": "https://avatars.githubusercontent.com/u/198768389?u=b3865cd31f1b64b307fa5da9ca1a73e1dbe6bcd5&v=4&s=40"
    },
    {
      "rank": 72,
      "username": "Rick1330",
      "realname": "Elshaday Mengesha",
      "profile": "https://github.com/Rick1330",
      "commits": 686,
      "avatar": "https://avatars.githubusercontent.com/u/133630952?u=c3324e075417f955e9e2496f5ed3ee1e9531c1f4&v=4&s=40"
    },
    {
      "rank": 73,
      "username": "ubeyidah",
      "realname": "Ubeyidah",
      "profile": "https://github.com/ubeyidah",
      "commits": 683,
      "avatar": "https://avatars.githubusercontent.com/u/159727076?u=398a5210bca59ed8554a7eab84fde65df86f0c3a&v=4&s=40"
    },
    {
      "rank": 74,
      "username": "Atnabon",
      "realname": "Atnabon Deressa",
      "profile": "https://github.com/Atnabon",
      "commits": 676,
      "avatar": "https://avatars.githubusercontent.com/u/99293642?u=b57a56d51980aa354efea9b9e835b81302771062&v=4&s=40"
    },
    {
      "rank": 75,
      "username": "rav3n11",
      "realname": "Bereket Terefe",
      "profile": "https://github.com/rav3n11",
      "commits": 667,
      "avatar": "https://avatars.githubusercontent.com/u/49443576?u=cc188d02a641601cb3a41a75b3519cb4bb08789d&v=4&s=40"
    },
    {
      "rank": 76,
      "username": "mesfind",
      "realname": "Mesfin Diro (PhD",
      "profile": "https://github.com/mesfind",
      "commits": 663,
      "avatar": "https://avatars.githubusercontent.com/u/22774778?u=522c2ee444876ea0af35630173ab12337cd12e1c&v=4&s=40"
    },
    {
      "rank": 77,
      "username": "nahomWM",
      "realname": "nahom weldemedhin",
      "profile": "https://github.com/nahomWM",
      "commits": 650,
      "avatar": "https://avatars.githubusercontent.com/u/216862887?v=4&s=40"
    },
    {
      "rank": 78,
      "username": "aelaf-git",
      "realname": "Aelaf Eskindir Abebe",
      "profile": "https://github.com/aelaf-git",
      "commits": 645,
      "avatar": "https://avatars.githubusercontent.com/u/200469519?u=5d1e40de78b5a7e1e14ceebb2f1cf751dadc1d28&v=4&s=40"
    },
    {
      "rank": 79,
      "username": "Yaya1200",
      "realname": "Yared Gebre",
      "profile": "https://github.com/Yaya1200",
      "commits": 642,
      "avatar": "https://avatars.githubusercontent.com/u/174056755?u=fb62425beee8da535b255547239af6b40e73f4a8&v=4&s=40"
    },
    {
      "rank": 80,
      "username": "Samrawit-alemu",
      "realname": "Samrawit Alemu",
      "profile": "https://github.com/Samrawit-alemu",
      "commits": 640,
      "avatar": "https://avatars.githubusercontent.com/u/152712148?u=6082bc882f0dd9216505c4826a0daf036074eb79&v=4&s=40"
    },
    {
      "rank": 81,
      "username": "bogoreh",
      "profile": "https://github.com/bogoreh",
      "commits": 619,
      "avatar": "https://avatars.githubusercontent.com/u/76124689?u=b432645e48a62dfdfa51e06780f30aa19431706b&v=4&s=40"
    },
    {
      "rank": 82,
      "username": "SKAT-16",
      "realname": "Nati G",
      "profile": "https://github.com/SKAT-16",
      "commits": 618,
      "avatar": "https://avatars.githubusercontent.com/u/94533342?u=29cf006a5b15f75fc347cf3cd4622b7ca484e704&v=4&s=40"
    },
    {
      "rank": 83,
      "username": "Eul45",
      "realname": "Eyuel Engida",
      "profile": "https://github.com/Eul45",
      "commits": 599,
      "avatar": "https://avatars.githubusercontent.com/u/176154715?u=9b10fcc252d96badaf303f0fa967c57a5ee428ca&v=4&s=40"
    },
    {
      "rank": 84,
      "username": "bezawitassaye",
      "realname": "Bezawit Assaye",
      "profile": "https://github.com/bezawitassaye",
      "commits": 599,
      "avatar": "https://avatars.githubusercontent.com/u/119955274?u=9f52f6162a283f621d048e1362e8e0e33108c301&v=4&s=40"
    },
    {
      "rank": 85,
      "username": "BinaDev29",
      "realname": "꧁༒☬ᶜᴿᴬᶻᵞkíllє®™r☬༒꧂",
      "profile": "https://github.com/BinaDev29",
      "commits": 595,
      "avatar": "https://avatars.githubusercontent.com/u/201996932?u=e205b23aae7965dbc3492db0fee54c7cb0ab209f&v=4&s=40"
    },
    {
      "rank": 86,
      "username": "shmuye",
      "realname": "Shmuye Ayalneh",
      "profile": "https://github.com/shmuye",
      "commits": 592,
      "avatar": "https://avatars.githubusercontent.com/u/167541848?u=9ecd0493872a8bbae3f47c869879bcaf702bfad3&v=4&s=40"
    },
    {
      "rank": 87,
      "username": "eyos-ias",
      "realname": "Eyosias",
      "profile": "https://github.com/eyos-ias",
      "commits": 586,
      "avatar": "https://avatars.githubusercontent.com/u/75771087?u=b69d6c93db686ed89d721ba78b8a9aeb9167381a&v=4&s=40"
    },
    {
      "rank": 88,
      "username": "natanmuletahunde",
      "realname": "pivnati",
      "profile": "https://github.com/natanmuletahunde",
      "commits": 584,
      "avatar": "https://avatars.githubusercontent.com/u/144028875?v=4&s=40"
    },
    {
      "rank": 89,
      "username": "Kidus-Nesibu",
      "realname": "Kidus Nesibu",
      "profile": "https://github.com/Kidus-Nesibu",
      "commits": 577,
      "avatar": "https://avatars.githubusercontent.com/u/118051709?u=c34a5d7ecb87cc9fa65ba93c602ef1dd8b8f2315&v=4&s=40"
    },
    {
      "rank": 90,
      "username": "getishe",
      "realname": "Getahune Alemayhu",
      "profile": "https://github.com/getishe",
      "commits": 575,
      "avatar": "https://avatars.githubusercontent.com/u/80521478?u=800a0cef9712b6db8d4c42e23158fdefb64f73b0&v=4&s=40"
    },
    {
      "rank": 91,
      "username": "Sihamkassim",
      "realname": "Siham Kassim",
      "profile": "https://github.com/Sihamkassim",
      "commits": 572,
      "avatar": "https://avatars.githubusercontent.com/u/152332445?u=9974187e56979a1c071fcd66be015cca5e77e34d&v=4&s=40"
    },
    {
      "rank": 92,
      "username": "sifenfisaha",
      "realname": "Sifen Fisaha",
      "profile": "https://github.com/sifenfisaha",
      "commits": 571,
      "avatar": "https://avatars.githubusercontent.com/u/190786260?u=2f6afe6309e0d64e6b1739b49a7b12402178723d&v=4&s=40"
    },
    {
      "rank": 93,
      "username": "anaol216",
      "realname": "Anaol Atinafu",
      "profile": "https://github.com/anaol216",
      "commits": 567,
      "avatar": "https://avatars.githubusercontent.com/u/137703580?u=bce17609dfb8f965b1aae1cf48369e98ce3f75c7&v=4&s=40"
    },
    {
      "rank": 94,
      "username": "surafelx",
      "realname": "Surafel Yimam",
      "profile": "https://github.com/surafelx",
      "commits": 564,
      "avatar": "https://avatars.githubusercontent.com/u/63095824?u=814c4bb88027797788cdffa61d289ba6a89e6ce2&v=4&s=40"
    },
    {
      "rank": 95,
      "username": "hosanna1616",
      "profile": "https://github.com/hosanna1616",
      "commits": 562,
      "avatar": "https://avatars.githubusercontent.com/u/192518825?u=ec6e16fc2f12654053178eae860c18aaa1cc7e66&v=4&s=40"
    },
    {
      "rank": 96,
      "username": "haftamudesta",
      "realname": "Haftamu Desta",
      "profile": "https://github.com/haftamudesta",
      "commits": 561,
      "avatar": "https://avatars.githubusercontent.com/u/99684109?u=aefe73c6a477b392a839ce49bc7556faf35ff8e4&v=4&s=40"
    },
    {
      "rank": 97,
      "username": "yohannes-wegayehu",
      "realname": "Yohannes Wegayehu",
      "profile": "https://github.com/yohannes-wegayehu",
      "commits": 553,
      "avatar": "https://avatars.githubusercontent.com/u/206997736?u=8efcdaf6a2ecd11e48fe78aede74219d57ef8767&v=4&s=40"
    },
    {
      "rank": 98,
      "username": "metiinie",
      "realname": "Awol Ibrahim",
      "profile": "https://github.com/metiinie",
      "commits": 551,
      "avatar": "https://avatars.githubusercontent.com/u/196482966?u=43fd92209f96c7ede597a8d75f3e8287c9f89d0b&v=4&s=40"
    },
    {
      "rank": 99,
      "username": "demirewu-manidefro",
      "realname": "Demirewu Manidefro",
      "profile": "https://github.com/demirewu-manidefro",
      "commits": 548,
      "avatar": "https://avatars.githubusercontent.com/u/187315312?u=2f21c8eefb3260f565f8b43289e443bfa4f0da4d&v=4&s=40"
    },
    {
      "rank": 100,
      "username": "FedhiJob",
      "realname": "Fedasa Eyob",
      "profile": "https://github.com/FedhiJob",
      "commits": 537,
      "avatar": "https://avatars.githubusercontent.com/u/165522312?u=13a946bfec381b18a31ef985c5928b23af95ae6f&v=4&s=40"
    },
    {
      "rank": 101,
      "username": "samwondim",
      "realname": "Samuel B. Wondimagegnehu",
      "profile": "https://github.com/samwondim",
      "commits": 535,
      "avatar": "https://avatars.githubusercontent.com/u/99725255?u=91cdefb02e3453add60bf43ada8a781c34e97b6e&v=4&s=40"
    },
    {
      "rank": 102,
      "username": "code-Estif",
      "realname": "Estif Dev",
      "profile": "https://github.com/code-Estif",
      "commits": 535,
      "avatar": "https://avatars.githubusercontent.com/u/220752714?u=f3b86884bb7704087a643b72dab3b94364fd3b43&v=4&s=40"
    },
    {
      "rank": 103,
      "username": "solomon-mh",
      "realname": "Solomon Muhye",
      "profile": "https://github.com/solomon-mh",
      "commits": 529,
      "avatar": "https://avatars.githubusercontent.com/u/132606059?v=4&s=40"
    },
    {
      "rank": 104,
      "username": "amanuel-alex",
      "realname": "Amanuel Alemayehu",
      "profile": "https://github.com/amanuel-alex",
      "commits": 524,
      "avatar": "https://avatars.githubusercontent.com/u/129431354?u=6b9a67cad4adf532d9b5a8936da797932f1b7d6c&v=4&s=40"
    },
    {
      "rank": 105,
      "username": "KryptonScript",
      "realname": "Krypton ♱👨🏾‍💻",
      "profile": "https://github.com/KryptonScript",
      "commits": 521,
      "avatar": "https://avatars.githubusercontent.com/u/227115784?u=3c3552f6f1f843213d2d8899b9f1545807eaca2f&v=4&s=40"
    },
    {
      "rank": 106,
      "username": "meke16",
      "realname": "Cherinet Habtamu",
      "profile": "https://github.com/meke16",
      "commits": 516,
      "avatar": "https://avatars.githubusercontent.com/u/192334560?u=7582dc760069d931e15c1216f9cf76319c41877e&v=4&s=40"
    },
    {
      "rank": 107,
      "username": "Yehonatal",
      "realname": "Yonatan Afewerk Teshome",
      "profile": "https://github.com/Yehonatal",
      "commits": 511,
      "avatar": "https://avatars.githubusercontent.com/u/83646080?u=dc29174ca484e1deba4e5faf3e901f7847a2cf5e&v=4&s=40"
    },
    {
      "rank": 108,
      "username": "kaleabAlemayehu",
      "realname": "Kaleab Alemayehu",
      "profile": "https://github.com/kaleabAlemayehu",
      "commits": 511,
      "avatar": "https://avatars.githubusercontent.com/u/116624166?u=1346d761a27371109aa5cb57545e243ef8a2687c&v=4&s=40"
    },
    {
      "rank": 109,
      "username": "naolaboma",
      "realname": "Naol Aboma",
      "profile": "https://github.com/naolaboma",
      "commits": 509,
      "avatar": "https://avatars.githubusercontent.com/u/153062988?u=3a84ed8db5d704da4838f3ba3f720534406456bc&v=4&s=40"
    },
    {
      "rank": 110,
      "username": "Yoni-Berihun",
      "realname": "Yonatan Berihun",
      "profile": "https://github.com/Yoni-Berihun",
      "commits": 499,
      "avatar": "https://avatars.githubusercontent.com/u/167955229?u=6b47c4b6127a2339bb83d19f58996cd225c71f7a&v=4&s=40"
    },
    {
      "rank": 111,
      "username": "abriham-atinkut",
      "realname": "Abriham Atinkut",
      "profile": "https://github.com/abriham-atinkut",
      "commits": 498,
      "avatar": "https://avatars.githubusercontent.com/u/225180618?u=43e49bbd8fd0c2bbec58c9ad18fa9268e943f2b1&v=4&s=40"
    },
    {
      "rank": 112,
      "username": "mikiyas-degefu",
      "realname": "Mikiyas Degefu",
      "profile": "https://github.com/mikiyas-degefu",
      "commits": 495,
      "avatar": "https://avatars.githubusercontent.com/u/80261020?u=94dc9887a3d80a75349138e2dfed453d0dc110a2&v=4&s=40"
    },
    {
      "rank": 113,
      "username": "tsionbirhanu",
      "realname": "Tsion Birhanu",
      "profile": "https://github.com/tsionbirhanu",
      "commits": 487,
      "avatar": "https://avatars.githubusercontent.com/u/168160291?u=db661ed490374db78bbc066a367db0c7038ba8ba&v=4&s=40"
    },
    {
      "rank": 114,
      "username": "bonssss",
      "realname": "Bonsa Desalegn",
      "profile": "https://github.com/bonssss",
      "commits": 486,
      "avatar": "https://avatars.githubusercontent.com/u/128582091?u=5b4e320ab792ed795647c607d4c6d1728c127814&v=4&s=40"
    },
    {
      "rank": 115,
      "username": "bati58",
      "realname": "bati jano",
      "profile": "https://github.com/bati58",
      "commits": 482,
      "avatar": "https://avatars.githubusercontent.com/u/197773134?u=383ea72b82ba22d79c071a9230880a266f08349f&v=4&s=40"
    },
    {
      "rank": 116,
      "username": "Kalkidan407",
      "realname": "Kalkidan Kelemework",
      "profile": "https://github.com/Kalkidan407",
      "commits": 481,
      "avatar": "https://avatars.githubusercontent.com/u/178004754?u=4b2dd8acb2c0f8067fefbcb5094459cf08b15de4&v=4&s=40"
    },
    {
      "rank": 117,
      "username": "nathanaelcheramlak",
      "realname": "Nathanael Cheramlak",
      "profile": "https://github.com/nathanaelcheramlak",
      "commits": 477,
      "avatar": "https://avatars.githubusercontent.com/u/124700160?u=6d3bf508312f998cbbf564552e5aa846bd9c6b11&v=4&s=40"
    },
    {
      "rank": 118,
      "username": "Ebo1996",
      "realname": "EBISA BERHANU",
      "profile": "https://github.com/Ebo1996",
      "commits": 473,
      "avatar": "https://avatars.githubusercontent.com/u/175691356?u=6858b4a52ae038a305e4990bb1782398cbbaeacc&v=4&s=40"
    },
    {
      "rank": 119,
      "username": "NebiyouBelaineh",
      "realname": "Nebiyou Belaineh",
      "profile": "https://github.com/NebiyouBelaineh",
      "commits": 472,
      "avatar": "https://avatars.githubusercontent.com/u/66259527?u=8f05473b02e0fe5e8e36bb1d2161226cd9d38b9b&v=4&s=40"
    },
    {
      "rank": 120,
      "username": "tsi1221",
      "realname": "tsehaynesh B.",
      "profile": "https://github.com/tsi1221",
      "commits": 472,
      "avatar": "https://avatars.githubusercontent.com/u/184611811?u=676f799621d3477b556d6b350885add9ec2c6970&v=4&s=40"
    },
    {
      "rank": 121,
      "username": "mubarek-hassen-buli",
      "realname": "Mubarek Hassen Buli",
      "profile": "https://github.com/mubarek-hassen-buli",
      "commits": 469,
      "avatar": "https://avatars.githubusercontent.com/u/199662473?u=532138ded2c3206cfe8003b1c1c90edae49d5db6&v=4&s=40"
    },
    {
      "rank": 122,
      "username": "Esubaalew",
      "realname": "Esubalew Chekol",
      "profile": "https://github.com/Esubaalew",
      "commits": 464,
      "avatar": "https://avatars.githubusercontent.com/u/106541640?u=ca419eb1ea0e4e2b8f6e89455de1f6e1d9e4e0c5&v=4&s=40"
    },
    {
      "rank": 123,
      "username": "Andu-alem",
      "realname": "Andualem Fereja B",
      "profile": "https://github.com/Andu-alem",
      "commits": 462,
      "avatar": "https://avatars.githubusercontent.com/u/79287341?u=ffac63e7631789738fa40e34c983635afd6faecc&v=4&s=40"
    },
    {
      "rank": 124,
      "username": "lisan-5",
      "realname": "Lisanegebriel Abay",
      "profile": "https://github.com/lisan-5",
      "commits": 449,
      "avatar": "https://avatars.githubusercontent.com/u/155144454?u=4e06ded7205d66dc081e2e13ebcd008acd18c406&v=4&s=40"
    },
    {
      "rank": 125,
      "username": "Dechie",
      "realname": "Dechasa Teshome",
      "profile": "https://github.com/Dechie",
      "commits": 447,
      "avatar": "https://avatars.githubusercontent.com/u/104849949?u=69701604e8780cd3425f551f7bb0d0eb23cb0c0b&v=4&s=40"
    },
    {
      "rank": 126,
      "username": "NatiDevHQ",
      "realname": "Natnael Getachew",
      "profile": "https://github.com/NatiDevHQ",
      "commits": 436,
      "avatar": "https://avatars.githubusercontent.com/u/185730705?u=32b992884da98d7a4f1da6d932a3a2393412b361&v=4&s=40"
    },
    {
      "rank": 127,
      "username": "muhammedb8826",
      "realname": "Muhammed Berisso",
      "profile": "https://github.com/muhammedb8826",
      "commits": 434,
      "avatar": "https://avatars.githubusercontent.com/u/115731485?u=019c9736a04d7a2b3c593eef7751e8f56bf8cc4e&v=4&s=40"
    },
    {
      "rank": 128,
      "username": "yonaries",
      "realname": "Yonathan Dejene",
      "profile": "https://github.com/yonaries",
      "commits": 432,
      "avatar": "https://avatars.githubusercontent.com/u/98046049?u=c9fdb5a151f5fb23f891b56b7dbc5d60c790ccb3&v=4&s=40"
    },
    {
      "rank": 129,
      "username": "kevenmuba",
      "realname": "Mubarek keven",
      "profile": "https://github.com/kevenmuba",
      "commits": 430,
      "avatar": "https://avatars.githubusercontent.com/u/168195414?u=b75ad157de7f6d2f95231f85a46c452f20e96aae&v=4&s=40"
    },
    {
      "rank": 130,
      "username": "MadisoMelese",
      "realname": "Madiso Melese",
      "profile": "https://github.com/MadisoMelese",
      "commits": 428,
      "avatar": "https://avatars.githubusercontent.com/u/157389082?u=5deda817ddf4b92a324c1908e72ab37e59b55f50&v=4&s=40"
    },
    {
      "rank": 131,
      "username": "chera-mihiretu",
      "realname": "Chera Mihiretu",
      "profile": "https://github.com/chera-mihiretu",
      "commits": 427,
      "avatar": "https://avatars.githubusercontent.com/u/63361469?v=4&s=40"
    },
    {
      "rank": 132,
      "username": "Nathanim1919",
      "realname": "Nathanim",
      "profile": "https://github.com/Nathanim1919",
      "commits": 424,
      "avatar": "https://avatars.githubusercontent.com/u/106013719?u=93060c3dc34498f1e6969f495a7454c064081198&v=4&s=40"
    },
    {
      "rank": 133,
      "username": "abdiladifrazaam",
      "realname": "Abdiladif Mohamoud",
      "profile": "https://github.com/abdiladifrazaam",
      "commits": 419,
      "avatar": "https://avatars.githubusercontent.com/u/171628367?u=d9c4029caa69c10e9d38e8f6c374c66eceb37bbe&v=4&s=40"
    },
    {
      "rank": 134,
      "username": "fitsumcs",
      "realname": "Fitsum Alemu",
      "profile": "https://github.com/fitsumcs",
      "commits": 419,
      "avatar": "https://avatars.githubusercontent.com/u/19759888?u=bad3bc6cd354b187f7e507e0d7bb910cd7cf9ff8&v=4&s=40"
    },
    {
      "rank": 135,
      "username": "NegusNati",
      "realname": "NATNAEL BIRHANU",
      "profile": "https://github.com/NegusNati",
      "commits": 416,
      "avatar": "https://avatars.githubusercontent.com/u/84500378?u=14ae5719ccc3a2c01a50db03a9c3ae1053fb66b2&v=4&s=40"
    },
    {
      "rank": 136,
      "username": "Meku-nint",
      "realname": "D_mekunint",
      "profile": "https://github.com/Meku-nint",
      "commits": 416,
      "avatar": "https://avatars.githubusercontent.com/u/154579159?u=898955ce9d23b47d111ec59d991ffbc7af20996a&v=4&s=40"
    },
    {
      "rank": 137,
      "username": "yihune1234",
      "realname": "yihune Belay Sebsibe",
      "profile": "https://github.com/yihune1234",
      "commits": 414,
      "avatar": "https://avatars.githubusercontent.com/u/197728600?u=88b09ccf5d533990b981021c680c20845b26b355&v=4&s=40"
    },
    {
      "rank": 138,
      "username": "deve1070",
      "realname": "Dawit Mekonnen Kasa",
      "profile": "https://github.com/deve1070",
      "commits": 413,
      "avatar": "https://avatars.githubusercontent.com/u/99678682?u=8003fcb940ef15788db4d6ca07a74a205a787f21&v=4&s=40"
    },
    {
      "rank": 139,
      "username": "Mubarek26",
      "realname": "Mubarek jemal Hassen",
      "profile": "https://github.com/Mubarek26",
      "commits": 410,
      "avatar": "https://avatars.githubusercontent.com/u/173202894?u=360deef47befc801bbad8954f02e358f50536f18&v=4&s=40"
    },
    {
      "rank": 140,
      "username": "edenWerke",
      "profile": "https://github.com/edenWerke",
      "commits": 409,
      "avatar": "https://avatars.githubusercontent.com/u/163598468?u=b28432b1393610be04abad1cf65196d1693f2746&v=4&s=40"
    },
    {
      "rank": 141,
      "username": "kenenisa",
      "realname": "Kenenisa Alemayehu",
      "profile": "https://github.com/kenenisa",
      "commits": 407,
      "avatar": "https://avatars.githubusercontent.com/u/53818162?u=21ee289edb74a85871634241ca2b73d10d14617d&v=4&s=40"
    },
    {
      "rank": 142,
      "username": "sgc93",
      "realname": "Smachew Gedefaw C.",
      "profile": "https://github.com/sgc93",
      "commits": 407,
      "avatar": "https://avatars.githubusercontent.com/u/109880887?u=95300a95c42e1fbb123b692e69cf6d017e11ef07&v=4&s=40"
    },
    {
      "rank": 143,
      "username": "Mistire",
      "realname": "Mistire",
      "profile": "https://github.com/Mistire",
      "commits": 401,
      "avatar": "https://avatars.githubusercontent.com/u/96515111?u=45c1c8a3bc3b19887268b2f89c4cb9cdaab5821c&v=4&s=40"
    },
    {
      "rank": 144,
      "username": "izzy-Ti",
      "realname": "israel A",
      "profile": "https://github.com/izzy-Ti",
      "commits": 397,
      "avatar": "https://avatars.githubusercontent.com/u/198761897?u=10752a7bfb0c269b89814c5fa1ebb44160a13e4d&v=4&s=40"
    },
    {
      "rank": 145,
      "username": "MohammedIbrahim8887",
      "realname": "Mohammed Ibrahim",
      "profile": "https://github.com/MohammedIbrahim8887",
      "commits": 396,
      "avatar": "https://avatars.githubusercontent.com/u/95257247?u=c40456e01a88d2417bcdeb0dbd3e4270e02e9964&v=4&s=40"
    },
    {
      "rank": 146,
      "username": "cherab19",
      "realname": "Cherenet Degefe",
      "profile": "https://github.com/cherab19",
      "commits": 394,
      "avatar": "https://avatars.githubusercontent.com/u/163351078?u=44bd3a8c946b5a02beeb8a97e5e39211652034a8&v=4&s=40"
    },
    {
      "rank": 147,
      "username": "Nahom32",
      "realname": "Nahom Senay",
      "profile": "https://github.com/Nahom32",
      "commits": 391,
      "avatar": "https://avatars.githubusercontent.com/u/70108056?u=2ff58c94f2d0164c681fa3416bcd8715dc2e2586&v=4&s=40"
    },
    {
      "rank": 148,
      "username": "sidocoder",
      "realname": "Sifhoran Regassa",
      "profile": "https://github.com/sidocoder",
      "commits": 390,
      "avatar": "https://avatars.githubusercontent.com/u/169819135?u=118cad8202145a81b6a4937a69cf022b72e3edc3&v=4&s=40"
    },
    {
      "rank": 149,
      "username": "yonasleykun27",
      "realname": "Yonas Leykun",
      "profile": "https://github.com/yonasleykun27",
      "commits": 388,
      "avatar": "https://avatars.githubusercontent.com/u/107372399?u=96e671bc2781e1d400064f8e851b3cf56a2e55e0&v=4&s=40"
    },
    {
      "rank": 150,
      "username": "Ludis-ET",
      "realname": "Ludis",
      "profile": "https://github.com/Ludis-ET",
      "commits": 378,
      "avatar": "https://avatars.githubusercontent.com/u/132431582?u=c37d014c87a3a2d119e1f224e39243a3f52a286e&v=4&s=40"
    },
    {
      "rank": 151,
      "username": "hunderaweke",
      "realname": "Hundera Awoke",
      "profile": "https://github.com/hunderaweke",
      "commits": 377,
      "avatar": "https://avatars.githubusercontent.com/u/112551317?u=1c679fda386554f5fcb7a5dda64476db7635c6fd&v=4&s=40"
    },
    {
      "rank": 152,
      "username": "teddy-a5",
      "realname": "Tewodros Anteneh",
      "profile": "https://github.com/teddy-a5",
      "commits": 374,
      "avatar": "https://avatars.githubusercontent.com/u/187751206?u=ee66c055fbb828c8fdcb21f6ff35f7983858912c&v=4&s=40"
    },
    {
      "rank": 153,
      "username": "amanuelbelete95",
      "realname": "Amanuel Belete",
      "profile": "https://github.com/amanuelbelete95",
      "commits": 371,
      "avatar": "https://avatars.githubusercontent.com/u/99336469?u=71f1c81917ba9ce2ea789d8103d27032f1c549e9&v=4&s=40"
    },
    {
      "rank": 154,
      "username": "BesufikadHosiso",
      "realname": "Besufikad Hosiso",
      "profile": "https://github.com/BesufikadHosiso",
      "commits": 369,
      "avatar": "https://avatars.githubusercontent.com/u/194159936?u=f2981e0c36ec5839238e8ec8deb8dbde85106d68&v=4&s=40"
    },
    {
      "rank": 155,
      "username": "dagmawibabi",
      "realname": "Dagmawi Babi",
      "profile": "https://github.com/dagmawibabi",
      "commits": 367,
      "avatar": "https://avatars.githubusercontent.com/u/44819176?u=29b1a624b4ec3b70f2fefea413d745af95c6d91b&v=4&s=40"
    },
    {
      "rank": 156,
      "username": "MichaelETPHP",
      "realname": "Michael Taye",
      "profile": "https://github.com/MichaelETPHP",
      "commits": 366,
      "avatar": "https://avatars.githubusercontent.com/u/87402911?u=b87f08bbef45e7891f2d5fde994cfd46b1d86ee4&v=4&s=40"
    },
    {
      "rank": 157,
      "username": "Fine-Guy-21",
      "realname": "Eyuel Solomon",
      "profile": "https://github.com/Fine-Guy-21",
      "commits": 366,
      "avatar": "https://avatars.githubusercontent.com/u/122565078?u=63508e4c6a3f5644f4d4d889f78672e1be82f5b9&v=4&s=40"
    },
    {
      "rank": 158,
      "username": "Yab112",
      "realname": "Coded-Fossil",
      "profile": "https://github.com/Yab112",
      "commits": 363,
      "avatar": "https://avatars.githubusercontent.com/u/106923105?u=c191cf7eb88bfc938cffc9c87fe936ed81e3f800&v=4&s=40"
    },
    {
      "rank": 159,
      "username": "Annabdiyu",
      "realname": "Anna Abdiyu",
      "profile": "https://github.com/Annabdiyu",
      "commits": 360,
      "avatar": "https://avatars.githubusercontent.com/u/178793811?u=dd48c4d726904fc89d524c0a5e5f497fe5943b92&v=4&s=40"
    },
    {
      "rank": 160,
      "username": "YonSci",
      "realname": "Yonas M.",
      "profile": "https://github.com/YonSci",
      "commits": 355,
      "avatar": "https://avatars.githubusercontent.com/u/20817023?u=fe4890d770f4a522a4cf0dce7282d950fb0910ed&v=4&s=40"
    },
    {
      "rank": 161,
      "username": "Ahlamv",
      "realname": "Ahlam Ahmed",
      "profile": "https://github.com/Ahlamv",
      "commits": 347,
      "avatar": "https://avatars.githubusercontent.com/u/186401048?v=4&s=40"
    },
    {
      "rank": 162,
      "username": "chalasimon",
      "realname": "chalasimon",
      "profile": "https://github.com/chalasimon",
      "commits": 341,
      "avatar": "https://avatars.githubusercontent.com/u/26658543?u=7930ce3d774dd6dd87ca8b5bd46925f178cb857c&v=4&s=40"
    },
    {
      "rank": 163,
      "username": "meherett",
      "realname": "Meheret",
      "profile": "https://github.com/meherett",
      "commits": 340,
      "avatar": "https://avatars.githubusercontent.com/u/30933405?u=3f42c719c201d07beb0de2c6c2a363a9f11c4d71&v=4&s=40"
    },
    {
      "rank": 164,
      "username": "Dach-JL",
      "realname": "Dedecho Jemal",
      "profile": "https://github.com/Dach-JL",
      "commits": 338,
      "avatar": "https://avatars.githubusercontent.com/u/192032086?u=dc1409e78ff3fc8aa35e5bf85e4173a53b32b6b2&v=4&s=40"
    },
    {
      "rank": 165,
      "username": "Yagth",
      "realname": "Yeabesera Derese",
      "profile": "https://github.com/Yagth",
      "commits": 337,
      "avatar": "https://avatars.githubusercontent.com/u/92119273?u=6fa5a9fdc2e56ae9c5030d1195888a41cf70e37e&v=4&s=40"
    },
    {
      "rank": 166,
      "username": "yaredow",
      "realname": "Yared Yilma",
      "profile": "https://github.com/yaredow",
      "commits": 336,
      "avatar": "https://avatars.githubusercontent.com/u/87979010?u=ae5cbc0b795afbc7227070b49d10df0e62cc7da8&v=4&s=40"
    },
    {
      "rank": 167,
      "username": "firoliyos",
      "realname": "FIRAOL T.",
      "profile": "https://github.com/firoliyos",
      "commits": 336,
      "avatar": "https://avatars.githubusercontent.com/u/121613862?v=4&s=40"
    },
    {
      "rank": 168,
      "username": "Muhammed-shamsadin",
      "realname": "Muhammed Samson",
      "profile": "https://github.com/Muhammed-shamsadin",
      "commits": 334,
      "avatar": "https://avatars.githubusercontent.com/u/111194652?u=6077ea4396f759dd05fd7d59f9f53ccbbc5699b9&v=4&s=40"
    },
    {
      "rank": 169,
      "username": "MRQ67",
      "realname": "Abdellah Qadi",
      "profile": "https://github.com/MRQ67",
      "commits": 332,
      "avatar": "https://avatars.githubusercontent.com/u/81095407?u=12131aeea8648e66067ae8e41bc1a3e03f61f2dc&v=4&s=40"
    },
    {
      "rank": 170,
      "username": "abnsol",
      "realname": "Abenezer Solomon",
      "profile": "https://github.com/abnsol",
      "commits": 331,
      "avatar": "https://avatars.githubusercontent.com/u/148258001?u=24eb9c02f296ed1426b06d08ac38b53cad33a3e3&v=4&s=40"
    },
    {
      "rank": 171,
      "username": "haxurn",
      "realname": "Samson Tesfaye",
      "profile": "https://github.com/haxurn",
      "commits": 331,
      "avatar": "https://avatars.githubusercontent.com/u/124459773?u=93b1a03ee69954d24a1cf095a14e5687f11b931b&v=4&s=40"
    },
    {
      "rank": 172,
      "username": "eyob13-coder",
      "realname": "Eyob",
      "profile": "https://github.com/eyob13-coder",
      "commits": 328,
      "avatar": "https://avatars.githubusercontent.com/u/157361748?u=2064f3c94f4b984c8b38db63116c8502289573b3&v=4&s=40"
    },
    {
      "rank": 173,
      "username": "Henok0728",
      "realname": "Henok Gizaw",
      "profile": "https://github.com/Henok0728",
      "commits": 325,
      "avatar": "https://avatars.githubusercontent.com/u/169617350?u=2b0074d69b752d0520ff081191e88a74f6a614a0&v=4&s=40"
    },
    {
      "rank": 174,
      "username": "bayillag",
      "realname": "Bayilla Geda",
      "profile": "https://github.com/bayillag",
      "commits": 323,
      "avatar": "https://avatars.githubusercontent.com/u/98712399?u=a76a7896d794fc5f7bcde9dd3b8fc6028bc3ac4d&v=4&s=40"
    },
    {
      "rank": 175,
      "username": "amanabate",
      "realname": "Amanuel Abate",
      "profile": "https://github.com/amanabate",
      "commits": 323,
      "avatar": "https://avatars.githubusercontent.com/u/129896984?u=3f5f2b89be965494c9deca917d6c79533305a5f6&v=4&s=40"
    },
    {
      "rank": 176,
      "username": "Muller1616",
      "realname": "Mulugeta",
      "profile": "https://github.com/Muller1616",
      "commits": 319,
      "avatar": "https://avatars.githubusercontent.com/u/183144163?u=86b39242ca17a632508f42cefd667c5262fe7e7c&v=4&s=40"
    },
    {
      "rank": 177,
      "username": "barekegnn",
      "realname": "Barekegn Asefa",
      "profile": "https://github.com/barekegnn",
      "commits": 318,
      "avatar": "https://avatars.githubusercontent.com/u/152094105?u=456c9a2d91a79d1cd5ec7a091f91ea95a6c29931&v=4&s=40"
    },
    {
      "rank": 178,
      "username": "surraaI",
      "realname": "Sura Itana",
      "profile": "https://github.com/surraaI",
      "commits": 317,
      "avatar": "https://avatars.githubusercontent.com/u/141846629?u=351ed283e5dd95c034ba65c1046c8a9d1e6eb5eb&v=4&s=40"
    },
    {
      "rank": 179,
      "username": "sultan3141",
      "realname": "Sultan Adinan",
      "profile": "https://github.com/sultan3141",
      "commits": 316,
      "avatar": "https://avatars.githubusercontent.com/u/194616055?u=7bec17df44e2ac9f4f5d6e415e9a641120cba39a&v=4&s=40"
    },
    {
      "rank": 180,
      "username": "kitessafikadu",
      "realname": "Kitessa Fikadu",
      "profile": "https://github.com/kitessafikadu",
      "commits": 313,
      "avatar": "https://avatars.githubusercontent.com/u/148215887?u=33cdb334ef252e472931be093502ec33371814fe&v=4&s=40"
    },
    {
      "rank": 181,
      "username": "Elizura",
      "realname": "Elisur Freyesus",
      "profile": "https://github.com/Elizura",
      "commits": 312,
      "avatar": "https://avatars.githubusercontent.com/u/98797447?u=7ea42954554da72aaf204ce075f7330b73ae6c1c&v=4&s=40"
    },
    {
      "rank": 182,
      "username": "Eliphaz21",
      "realname": "Yeabsra Andnet",
      "profile": "https://github.com/Eliphaz21",
      "commits": 310,
      "avatar": "https://avatars.githubusercontent.com/u/176462637?u=bad147061f4ccf0891245a3bd2136de088a0e872&v=4&s=40"
    },
    {
      "rank": 183,
      "username": "Gadisa16",
      "realname": "Gadisa Kanchora Wolde",
      "profile": "https://github.com/Gadisa16",
      "commits": 309,
      "avatar": "https://avatars.githubusercontent.com/u/133113137?u=63c964df975669a95e7b90d13d3f9310e66fd928&v=4&s=40"
    },
    {
      "rank": 184,
      "username": "bonatolasa",
      "realname": "BonaTolasa",
      "profile": "https://github.com/bonatolasa",
      "commits": 308,
      "avatar": "https://avatars.githubusercontent.com/u/146835715?u=1d7918258be58dd844c894c817e78a98343a7ac5&v=4&s=40"
    },
    {
      "rank": 185,
      "username": "EphriamHab",
      "realname": "Ephrem Habtamu",
      "profile": "https://github.com/EphriamHab",
      "commits": 307,
      "avatar": "https://avatars.githubusercontent.com/u/117913070?u=a938e919dbf0383b290467b845943f9954fc3801&v=4&s=40"
    },
    {
      "rank": 186,
      "username": "haileznabu",
      "realname": "HAILE ZNABU",
      "profile": "https://github.com/haileznabu",
      "commits": 306,
      "avatar": "https://avatars.githubusercontent.com/u/43222722?u=d9301ebe5ee2daaedee8298b89cd95dba9f82432&v=4&s=40"
    },
    {
      "rank": 187,
      "username": "kumsa-Mergia",
      "realname": "Kumsa Mergia",
      "profile": "https://github.com/kumsa-Mergia",
      "commits": 305,
      "avatar": "https://avatars.githubusercontent.com/u/65948114?u=835ca55addd127a29f576f13d8fb628c5282d446&v=4&s=40"
    },
    {
      "rank": 188,
      "username": "olyadboka",
      "realname": "Olyad Boka",
      "profile": "https://github.com/olyadboka",
      "commits": 304,
      "avatar": "https://avatars.githubusercontent.com/u/193741868?u=8be96445245465a96e4246075b0bca430fa69e5c&v=4&s=40"
    },
    {
      "rank": 189,
      "username": "yeab-dev",
      "realname": "Yeab",
      "profile": "https://github.com/yeab-dev",
      "commits": 304,
      "avatar": "https://avatars.githubusercontent.com/u/144266037?u=9d797a40dd8c77493e25ca691a2bacccd74480ee&v=4&s=40"
    },
    {
      "rank": 190,
      "username": "fenan-yosef",
      "realname": "Fenan",
      "profile": "https://github.com/fenan-yosef",
      "commits": 301,
      "avatar": "https://avatars.githubusercontent.com/u/114949236?u=10c41b503d9710ab3a94d24dd4e134f3908f968c&v=4&s=40"
    },
    {
      "rank": 191,
      "username": "UbdaNam",
      "realname": "Abdurahim .M",
      "profile": "https://github.com/UbdaNam",
      "commits": 295,
      "avatar": "https://avatars.githubusercontent.com/u/66268418?u=b14889c13218a5932373720daa5a83d91d8af766&v=4&s=40"
    },
    {
      "rank": 192,
      "username": "Tommy-devgit",
      "realname": "Tomas Melesse",
      "profile": "https://github.com/Tommy-devgit",
      "commits": 288,
      "avatar": "https://avatars.githubusercontent.com/u/201990122?u=ec28ffb0af4671f93af28c63a06f28f0a0976648&v=4&s=40"
    },
    {
      "rank": 193,
      "username": "eyuBirhanu",
      "realname": "Eyu Birhanu",
      "profile": "https://github.com/eyuBirhanu",
      "commits": 284,
      "avatar": "https://avatars.githubusercontent.com/u/151485420?u=54e3eed911670ddf564c5b22e6348fe5663fddf6&v=4&s=40"
    },
    {
      "rank": 194,
      "username": "nafargi",
      "realname": "Nafargi Damena",
      "profile": "https://github.com/nafargi",
      "commits": 284,
      "avatar": "https://avatars.githubusercontent.com/u/143782082?u=33545056892db0455dad5f864fde3a80ef787596&v=4&s=40"
    },
    {
      "rank": 195,
      "username": "lijsamuael",
      "realname": "Sami",
      "profile": "https://github.com/lijsamuael",
      "commits": 280,
      "avatar": "https://avatars.githubusercontent.com/u/101696125?u=4d7f104cb9e59b86947d4765369ce4d4251614f9&v=4&s=40"
    },
    {
      "rank": 196,
      "username": "HyoketsuSenpai",
      "realname": "Yosefe Tilahun",
      "profile": "https://github.com/HyoketsuSenpai",
      "commits": 279,
      "avatar": "https://avatars.githubusercontent.com/u/116489282?u=ece3b864b550422e6ac2ff3fdf5413aaa47368a6&v=4&s=40"
    },
    {
      "rank": 197,
      "username": "abeltyr",
      "realname": "Abel Lamesgen",
      "profile": "https://github.com/abeltyr",
      "commits": 277,
      "avatar": "https://avatars.githubusercontent.com/u/30269130?u=ec89f45d7f192e811317c9e27735d1172d80dede&v=4&s=40"
    },
    {
      "rank": 198,
      "username": "abi556",
      "realname": "Abiy Hailu Getachew",
      "profile": "https://github.com/abi556",
      "commits": 277,
      "avatar": "https://avatars.githubusercontent.com/u/134966562?u=0b7630541dca1a44b61ed31ad1f1e1b4f59d3c49&v=4&s=40"
    },
    {
      "rank": 199,
      "username": "daniel-bogale",
      "realname": "Daniel Bogale",
      "profile": "https://github.com/daniel-bogale",
      "commits": 275,
      "avatar": "https://avatars.githubusercontent.com/u/104236560?u=f389c383b9ce7de1f003eaf8084861e5581f8f08&v=4&s=40"
    },
    {
      "rank": 200,
      "username": "daveragos",
      "realname": "Dawit Beyene",
      "profile": "https://github.com/daveragos",
      "commits": 274,
      "avatar": "https://avatars.githubusercontent.com/u/96292329?u=476e6ff6f7a8027dfb263658ec245fe2442bf860&v=4&s=40"
    },
    {
      "rank": 201,
      "username": "AnexDev1",
      "realname": "Anwar Nasir",
      "profile": "https://github.com/AnexDev1",
      "commits": 273,
      "avatar": "https://avatars.githubusercontent.com/u/92826091?u=c1a49064ae909e595f9e4a50913706812d0d78e5&v=4&s=40"
    },
    {
      "rank": 202,
      "username": "Bushra-KB",
      "realname": "Bushra Kidanemariam",
      "profile": "https://github.com/Bushra-KB",
      "commits": 273,
      "avatar": "https://avatars.githubusercontent.com/u/29249243?u=b1caac72ff8f552f1fc6d4204d9ded0e5c77e176&v=4&s=40"
    },
    {
      "rank": 203,
      "username": "ERMIASWAKGARI",
      "realname": "Ermias Wakgari Yadeta",
      "profile": "https://github.com/ERMIASWAKGARI",
      "commits": 272,
      "avatar": "https://avatars.githubusercontent.com/u/118937954?u=e3bdc958efabcdc03b2c1843b2b0986d9ca33029&v=4&s=40"
    },
    {
      "rank": 204,
      "username": "fafiyusuf",
      "realname": "Fetiya Yusuf",
      "profile": "https://github.com/fafiyusuf",
      "commits": 272,
      "avatar": "https://avatars.githubusercontent.com/u/152329383?u=0d1814013200bcd4c7dfe1b50ad759075ad0a30a&v=4&s=40"
    },
    {
      "rank": 205,
      "username": "mumekonin",
      "realname": "MULUALEM MEKONIN",
      "profile": "https://github.com/mumekonin",
      "commits": 272,
      "avatar": "https://avatars.githubusercontent.com/u/180072762?u=38732396c4f11fbfbc5f85b0781ec50c32e03ca8&v=4&s=40"
    },
    {
      "rank": 206,
      "username": "banadawit",
      "realname": "Bana Dawit",
      "profile": "https://github.com/banadawit",
      "commits": 271,
      "avatar": "https://avatars.githubusercontent.com/u/129886937?u=1954161f9bac8e04bd2fc8cb1c8ca39a6a942fd9&v=4&s=40"
    },
    {
      "rank": 207,
      "username": "addispupi",
      "realname": "Addisu Hailemariam",
      "profile": "https://github.com/addispupi",
      "commits": 271,
      "avatar": "https://avatars.githubusercontent.com/u/72408025?u=9bb5a1ef12b8d3ec439078969e0df5b4eba24ada&v=4&s=40"
    },
    {
      "rank": 208,
      "username": "eendale",
      "realname": "Endale",
      "profile": "https://github.com/eendale",
      "commits": 270,
      "avatar": "https://avatars.githubusercontent.com/u/77967123?u=ee041c6b4df86c968b14545da13584b4a4b45cc9&v=4&s=40"
    },
    {
      "rank": 209,
      "username": "Ayida-Aman",
      "realname": "Ayida Aman Shifa",
      "profile": "https://github.com/Ayida-Aman",
      "commits": 267,
      "avatar": "https://avatars.githubusercontent.com/u/180939082?u=3e8d76a33adfc367098946aace84adf842352793&v=4&s=40"
    },
    {
      "rank": 210,
      "username": "squidward404",
      "realname": "Befikir Shimelis",
      "profile": "https://github.com/squidward404",
      "commits": 267,
      "avatar": "https://avatars.githubusercontent.com/u/161409855?u=d7257ce06d455e77af5cb5d9a3aa1e56a46578e1&v=4&s=40"
    },
    {
      "rank": 211,
      "username": "Misikerr",
      "realname": "Misiker_Genene",
      "profile": "https://github.com/Misikerr",
      "commits": 263,
      "avatar": "https://avatars.githubusercontent.com/u/146325517?u=4407c2202e539ef6dd2a75e60b97d4a0c384ab51&v=4&s=40"
    },
    {
      "rank": 212,
      "username": "Miheret-Girmachew",
      "realname": "Miheret Girmachew",
      "profile": "https://github.com/Miheret-Girmachew",
      "commits": 262,
      "avatar": "https://avatars.githubusercontent.com/u/124549518?u=e4f48ab44ac5e8f3ca088d9296def613f0d52b2b&v=4&s=40"
    },
    {
      "rank": 213,
      "username": "BEKI77",
      "realname": "BEREKET TADIWOS",
      "profile": "https://github.com/BEKI77",
      "commits": 260,
      "avatar": "https://avatars.githubusercontent.com/u/86204534?u=23fb3ad4189fd9e0d940b40026130536af1d9e0b&v=4&s=40"
    },
    {
      "rank": 214,
      "username": "tezena",
      "realname": "Tewodros Nibret Adal",
      "profile": "https://github.com/tezena",
      "commits": 258,
      "avatar": "https://avatars.githubusercontent.com/u/99950601?v=4&s=40"
    },
    {
      "rank": 215,
      "username": "Fasill",
      "realname": "FASIL",
      "profile": "https://github.com/Fasill",
      "commits": 257,
      "avatar": "https://avatars.githubusercontent.com/u/81506454?u=f2c9d797f18cac997dfaff1b79cbcedbb3fcedd9&v=4&s=40"
    },
    {
      "rank": 216,
      "username": "vernu",
      "realname": "vernu",
      "profile": "https://github.com/vernu",
      "commits": 256,
      "avatar": "https://avatars.githubusercontent.com/u/7479824?u=4533df09ccb692940e78a42dcecf1afe62daa517&v=4&s=40"
    },
    {
      "rank": 217,
      "username": "wendecoder",
      "realname": "Wondwossen Dufera",
      "profile": "https://github.com/wendecoder",
      "commits": 256,
      "avatar": "https://avatars.githubusercontent.com/u/56078297?u=cac9fd51a873f5e19deea99eb77d416b05e6cfe0&v=4&s=40"
    },
    {
      "rank": 218,
      "username": "beka-birhanu",
      "realname": "Beka B. Atomsa",
      "profile": "https://github.com/beka-birhanu",
      "commits": 253,
      "avatar": "https://avatars.githubusercontent.com/u/119675042?u=20f0220c1c34b127916baa81ad06961a127ac9e6&v=4&s=40"
    },
    {
      "rank": 219,
      "username": "bete7512",
      "realname": "Bete Goshme",
      "profile": "https://github.com/bete7512",
      "commits": 251,
      "avatar": "https://avatars.githubusercontent.com/u/99134122?u=e6d193c67a2f0a4ea2f88a35110ce927149c973d&v=4&s=40"
    },
    {
      "rank": 220,
      "username": "abrshiz",
      "realname": "Abrham Wendesen",
      "profile": "https://github.com/abrshiz",
      "commits": 250,
      "avatar": "https://avatars.githubusercontent.com/u/190122978?u=fbe90865f7fda48ebdd57773a8d270875212069e&v=4&s=40"
    },
    {
      "rank": 221,
      "username": "Yobil-Job",
      "realname": "Eyob Weldetensay",
      "profile": "https://github.com/Yobil-Job",
      "commits": 250,
      "avatar": "https://avatars.githubusercontent.com/u/167990260?u=1e138688196813fb59ac865990a2254fee29f880&v=4&s=40"
    },
    {
      "rank": 222,
      "username": "fahamijemal",
      "realname": "Fahami Jemal Harun",
      "profile": "https://github.com/fahamijemal",
      "commits": 249,
      "avatar": "https://avatars.githubusercontent.com/u/132432021?u=099e5e445a4b142da738af023a621f2175045f97&v=4&s=40"
    },
    {
      "rank": 223,
      "username": "abdureshidabdulahi",
      "realname": "Abdureshid Abdulahi",
      "profile": "https://github.com/abdureshidabdulahi",
      "commits": 249,
      "avatar": "https://avatars.githubusercontent.com/u/202524972?u=5fc869e6301ea5024b59269165ff58d077bdae7e&v=4&s=40"
    },
    {
      "rank": 224,
      "username": "Osamaseid",
      "realname": "OSAMA SEID",
      "profile": "https://github.com/Osamaseid",
      "commits": 247,
      "avatar": "https://avatars.githubusercontent.com/u/119799518?u=0eae0a38046dafbb23c125bdcdf8b0f3b7621670&v=4&s=40"
    },
    {
      "rank": 225,
      "username": "yeabtsega45",
      "realname": "Yeabtsega Yeshidnber",
      "profile": "https://github.com/yeabtsega45",
      "commits": 246,
      "avatar": "https://avatars.githubusercontent.com/u/118176644?u=844c8853fe0a18235d1e64b33d44ff5d7f94937f&v=4&s=40"
    },
    {
      "rank": 226,
      "username": "firomsahika",
      "realname": "Firomsa Hika",
      "profile": "https://github.com/firomsahika",
      "commits": 246,
      "avatar": "https://avatars.githubusercontent.com/u/116643596?u=5fc2fbac45c7f8794f3907e56e7c9b0d33a0c526&v=4&s=40"
    },
    {
      "rank": 227,
      "username": "zekariyasamdu",
      "realname": "Zach",
      "profile": "https://github.com/zekariyasamdu",
      "commits": 246,
      "avatar": "https://avatars.githubusercontent.com/u/130123502?u=edd068c291178d96a0384f68b78f42ac4cc441f6&v=4&s=40"
    },
    {
      "rank": 228,
      "username": "flavnat",
      "realname": "Natnael Ayele",
      "profile": "https://github.com/flavnat",
      "commits": 244,
      "avatar": "https://avatars.githubusercontent.com/u/154729622?u=1de838edd4edd56eb3af640efd0e1758dc033f21&v=4&s=40"
    },
    {
      "rank": 229,
      "username": "birhanu-dejen",
      "realname": "Birhanu Dejen",
      "profile": "https://github.com/birhanu-dejen",
      "commits": 243,
      "avatar": "https://avatars.githubusercontent.com/u/147509170?u=cc7303f922df169f0be92f0ccbe24ca3d077c613&v=4&s=40"
    },
    {
      "rank": 230,
      "username": "Besufekad-HAZ",
      "realname": "Besufekad Alemu",
      "profile": "https://github.com/Besufekad-HAZ",
      "commits": 242,
      "avatar": "https://avatars.githubusercontent.com/u/23375153?u=5e9fb2b24a273f9c0f0f1ca90643d15f7a5504cb&v=4&s=40"
    },
    {
      "rank": 231,
      "username": "MubarekAdem",
      "realname": "Mubarek",
      "profile": "https://github.com/MubarekAdem",
      "commits": 242,
      "avatar": "https://avatars.githubusercontent.com/u/156066237?u=52b2e0028ed76e2baab062ceb8ef171c8079497d&v=4&s=40"
    },
    {
      "rank": 232,
      "username": "Fenet-damena",
      "realname": "Fenet Damena",
      "profile": "https://github.com/Fenet-damena",
      "commits": 240,
      "avatar": "https://avatars.githubusercontent.com/u/138729138?u=7a93c1e8b43bb11f426a50b5be3023a61eac488c&v=4&s=40"
    },
    {
      "rank": 233,
      "username": "saron03",
      "realname": "Saron Yitbareck",
      "profile": "https://github.com/saron03",
      "commits": 237,
      "avatar": "https://avatars.githubusercontent.com/u/114290476?u=55f953567eb88ea835d915fa1e9eaaed7aec2b0a&v=4&s=40"
    },
    {
      "rank": 234,
      "username": "ephremdeme",
      "realname": "Ephrem Demelash",
      "profile": "https://github.com/ephremdeme",
      "commits": 234,
      "avatar": "https://avatars.githubusercontent.com/u/38384199?u=d9f3257f1f6e88805aa5dbe0974a3e8c215a766a&v=4&s=40"
    },
    {
      "rank": 235,
      "username": "rasyosef",
      "realname": "Yosef W. Alemneh",
      "profile": "https://github.com/rasyosef",
      "commits": 234,
      "avatar": "https://avatars.githubusercontent.com/u/37704356?u=e1111216b31b5ebce06a961ee10d472e25dfa4e5&v=4&s=40"
    },
    {
      "rank": 236,
      "username": "Joshz-090",
      "realname": "Eyasu Zerihun Asma",
      "profile": "https://github.com/Joshz-090",
      "commits": 232,
      "avatar": "https://avatars.githubusercontent.com/u/198375774?u=f0a7702f9897f0735ad7a241cbcf6b838a515084&v=4&s=40"
    },
    {
      "rank": 237,
      "username": "Fisseha-Estifanos",
      "realname": "Fisseha Estifanos",
      "profile": "https://github.com/Fisseha-Estifanos",
      "commits": 232,
      "avatar": "https://avatars.githubusercontent.com/u/74893977?u=a2982cf9bf62bc7c08a5268241b783abea04efd1&v=4&s=40"
    },
    {
      "rank": 238,
      "username": "tewodros-m",
      "realname": "Tewodros M.",
      "profile": "https://github.com/tewodros-m",
      "commits": 229,
      "avatar": "https://avatars.githubusercontent.com/u/117937212?u=981892668521a9131b8da727e38cd57003e6cb42&v=4&s=40"
    },
    {
      "rank": 239,
      "username": "epha-b1",
      "realname": "Ephrem Belaineh",
      "profile": "https://github.com/epha-b1",
      "commits": 226,
      "avatar": "https://avatars.githubusercontent.com/u/113988832?u=b27564c830daa6ac1be03f02a520a577ab80e7ea&v=4&s=40"
    },
    {
      "rank": 240,
      "username": "Dave-lab12",
      "realname": "Dawit Mekonnen",
      "profile": "https://github.com/Dave-lab12",
      "commits": 226,
      "avatar": "https://avatars.githubusercontent.com/u/56738450?u=836f1b5b7978f10abf4ac16d2a020c24cde62555&v=4&s=40"
    },
    {
      "rank": 241,
      "username": "gaddisa",
      "realname": "Gaddisa Olani Ganfure",
      "profile": "https://github.com/gaddisa",
      "commits": 225,
      "avatar": "https://avatars.githubusercontent.com/u/10139659?u=9e8eda7d213c7d9addbf7c9a4da6235922e0c9d8&v=4&s=40"
    },
    {
      "rank": 242,
      "username": "alan-sultan",
      "realname": "Alan Sultan",
      "profile": "https://github.com/alan-sultan",
      "commits": 224,
      "avatar": "https://avatars.githubusercontent.com/u/169437091?v=4&s=40"
    },
    {
      "rank": 243,
      "username": "Abel5173",
      "realname": "Abel",
      "profile": "https://github.com/Abel5173",
      "commits": 223,
      "avatar": "https://avatars.githubusercontent.com/u/86670708?u=68cb74ecc5814bd4863cade4dea8624f2f32f501&v=4&s=40"
    },
    {
      "rank": 244,
      "username": "BisRyy",
      "realname": "Bisrat Kebere",
      "profile": "https://github.com/BisRyy",
      "commits": 222,
      "avatar": "https://avatars.githubusercontent.com/u/87482476?u=9e89ca8c23b00290da8d5fd8c03b82ca25356855&v=4&s=40"
    },
    {
      "rank": 245,
      "username": "Dame-Abera",
      "realname": "Dame Abera",
      "profile": "https://github.com/Dame-Abera",
      "commits": 220,
      "avatar": "https://avatars.githubusercontent.com/u/161621839?u=d08f781181eb2d8267e0b88a231c3dae498c23ac&v=4&s=40"
    },
    {
      "rank": 246,
      "username": "RobaChimdesa",
      "realname": "Roba Chimdesa",
      "profile": "https://github.com/RobaChimdesa",
      "commits": 220,
      "avatar": "https://avatars.githubusercontent.com/u/130156480?u=bd1d5171cad5f2b95610c732da76ea109b41e29e&v=4&s=40"
    },
    {
      "rank": 247,
      "username": "gelila-d",
      "realname": "Gelila Dereje",
      "profile": "https://github.com/gelila-d",
      "commits": 218,
      "avatar": "https://avatars.githubusercontent.com/u/190993043?u=dbca747814eaca703c470b169cccc027f3d49d98&v=4&s=40"
    },
    {
      "rank": 248,
      "username": "Dagmawi-Y",
      "realname": "Dagmawi Hailu",
      "profile": "https://github.com/Dagmawi-Y",
      "commits": 218,
      "avatar": "https://avatars.githubusercontent.com/u/135310799?u=d7422e3ccbbe59d985faf4aec752b6d9738a25ca&v=4&s=40"
    },
    {
      "rank": 249,
      "username": "Ambesawi",
      "realname": "Aman Brhane",
      "profile": "https://github.com/Ambesawi",
      "commits": 214,
      "avatar": "https://avatars.githubusercontent.com/u/117799650?u=d91338d7ba51aa0888caeeb8d100f8eb083c3341&v=4&s=40"
    },
    {
      "rank": 250,
      "username": "mukesudo",
      "realname": "Mukhtar Saeed",
      "profile": "https://github.com/mukesudo",
      "commits": 211,
      "avatar": "https://avatars.githubusercontent.com/u/50199153?u=d6908dd62438d06c8071cf6412070a585595fa92&v=4&s=40"
    },
    {
      "rank": 251,
      "username": "MicrQ",
      "realname": "Abenet Gebre",
      "profile": "https://github.com/MicrQ",
      "commits": 209,
      "avatar": "https://avatars.githubusercontent.com/u/140071383?u=3439453365cec36d95dc5f59979b222c4f38b9ee&v=4&s=40"
    },
    {
      "rank": 252,
      "username": "Samuel-Fikre",
      "realname": "Samuel Fikre",
      "profile": "https://github.com/Samuel-Fikre",
      "commits": 207,
      "avatar": "https://avatars.githubusercontent.com/u/173048410?u=828869268d9f2250cabf6570619779a8b544be68&v=4&s=40"
    },
    {
      "rank": 253,
      "username": "Siraj-Abdulkadir",
      "realname": "Siraj Abdulkadir",
      "profile": "https://github.com/Siraj-Abdulkadir",
      "commits": 206,
      "avatar": "https://avatars.githubusercontent.com/u/188580884?u=2d3aacf7db12693573e23920fbbfffd0c1cc5dfb&v=4&s=40"
    },
    {
      "rank": 254,
      "username": "Elish-Ab",
      "realname": "Elisha Abriham",
      "profile": "https://github.com/Elish-Ab",
      "commits": 203,
      "avatar": "https://avatars.githubusercontent.com/u/116567028?u=99024a3db95a3f26a73170247d396db3fca1e5f4&v=4&s=40"
    },
    {
      "rank": 255,
      "username": "Blacknahil",
      "realname": "Nahom Garefo",
      "profile": "https://github.com/Blacknahil",
      "commits": 202,
      "avatar": "https://avatars.githubusercontent.com/u/119704083?u=e6123980dab1f94839631f0ce7d12d7f34f654e6&v=4&s=40"
    },
    {
      "rank": 256,
      "username": "Jeremi-code",
      "realname": "Ermias S. Deresse",
      "profile": "https://github.com/Jeremi-code",
      "commits": 202,
      "avatar": "https://avatars.githubusercontent.com/u/106976091?u=d7524d2960d3afd6ef4c53891bf94e20f81bdfcc&v=4&s=40"
    }
  ]
}
