{
  "country": {
    "slug": "morocco",
    "name": "Morocco"
  },
  "generatedAt": "2026-07-21T16:19:11.574Z",
  "users": [
    {
      "rank": 1,
      "username": "Mohammedcha",
      "realname": "Mohammed cha",
      "profile": "https://github.com/Mohammedcha",
      "commits": 13038,
      "avatar": "https://avatars.githubusercontent.com/u/40530012?u=98af635326e7a626440f07e43f7a08b0db3c65b2&v=4&s=40"
    },
    {
      "rank": 2,
      "username": "lfarssi",
      "realname": "MOHAMED EL FARSSI",
      "profile": "https://github.com/lfarssi",
      "commits": 10437,
      "avatar": "https://avatars.githubusercontent.com/u/119127725?u=32fea64ce5bff8660c4a89f58072bb53c8d95def&v=4&s=40"
    },
    {
      "rank": 3,
      "username": "fahdaguenouz",
      "realname": "Fahd Aguenouz",
      "profile": "https://github.com/fahdaguenouz",
      "commits": 8346,
      "avatar": "https://avatars.githubusercontent.com/u/120320573?u=59d88c83dcd6f56e16e7062d0a9d1d79cf1504f4&v=4&s=40"
    },
    {
      "rank": 4,
      "username": "zKhadiri",
      "realname": "Zakaria Khadiri",
      "profile": "https://github.com/zKhadiri",
      "commits": 6573,
      "avatar": "https://avatars.githubusercontent.com/u/43075184?v=4&s=40"
    },
    {
      "rank": 5,
      "username": "abdarrhmanessetaoui",
      "realname": "ABDERRAHMAN SETTAOUI",
      "profile": "https://github.com/abdarrhmanessetaoui",
      "commits": 4312,
      "avatar": "https://avatars.githubusercontent.com/u/185644219?u=2f0cf9011432c83f9cff7325d1af97b188396b91&v=4&s=40"
    },
    {
      "rank": 6,
      "username": "yoeunes",
      "realname": "Younes ENNAJI",
      "profile": "https://github.com/yoeunes",
      "commits": 2909,
      "avatar": "https://avatars.githubusercontent.com/u/10859693?u=dbeebd41666e217a0226f1a8b4b6efb93640ffa2&v=4&s=40"
    },
    {
      "rank": 7,
      "username": "EL-HOUSS-BRAHIM",
      "realname": "Brahim El Houss",
      "profile": "https://github.com/EL-HOUSS-BRAHIM",
      "commits": 2687,
      "avatar": "https://avatars.githubusercontent.com/u/87819687?u=0526d9eaa3c8e687cfe7d0dfb41ad7273b7cfb44&v=4&s=40"
    },
    {
      "rank": 8,
      "username": "ImadSaddik",
      "realname": "Imad Saddik",
      "profile": "https://github.com/ImadSaddik",
      "commits": 2408,
      "avatar": "https://avatars.githubusercontent.com/u/79410781?u=6f23f56e5eaef76fdbd0167681139d9f478418af&v=4&s=40"
    },
    {
      "rank": 9,
      "username": "ismail-en-niou",
      "realname": "ismail en-niou",
      "profile": "https://github.com/ismail-en-niou",
      "commits": 2321,
      "avatar": "https://avatars.githubusercontent.com/u/132809252?u=a423fc9012156e22124df85e7067fc73efb7193d&v=4&s=40"
    },
    {
      "rank": 10,
      "username": "seuros",
      "realname": "Abdelkader Boudih",
      "profile": "https://github.com/seuros",
      "commits": 2250,
      "avatar": "https://avatars.githubusercontent.com/u/2394703?u=db3bfddb34846d7b948b10aae2bc4b6398edad45&v=4&s=40"
    },
    {
      "rank": 11,
      "username": "Hi1talib1World",
      "realname": "hicham outaleb",
      "profile": "https://github.com/Hi1talib1World",
      "commits": 2203,
      "avatar": "https://avatars.githubusercontent.com/u/31773165?u=afc6d7b267c478c93234ae3a541ad5e4fffad543&v=4&s=40"
    },
    {
      "rank": 12,
      "username": "aymanebouljam",
      "realname": "Aymane Bouljam",
      "profile": "https://github.com/aymanebouljam",
      "commits": 1950,
      "avatar": "https://avatars.githubusercontent.com/u/235529830?u=7e042e8991574d9ce96620e21bdc01af598d6c78&v=4&s=40"
    },
    {
      "rank": 13,
      "username": "YounesBousfiha",
      "realname": "Younes Bousfiha",
      "profile": "https://github.com/YounesBousfiha",
      "commits": 1892,
      "avatar": "https://avatars.githubusercontent.com/u/125454968?u=ac7aa4f9fed3d6a4a75cb8f32691ac2bbae279ee&v=4&s=40"
    },
    {
      "rank": 14,
      "username": "jsflivedeus",
      "realname": "Walid BOUSSOU",
      "profile": "https://github.com/jsflivedeus",
      "commits": 1887,
      "avatar": "https://avatars.githubusercontent.com/u/635671?v=4&s=40"
    },
    {
      "rank": 15,
      "username": "hichamboushaba",
      "realname": "Hicham Boushaba",
      "profile": "https://github.com/hichamboushaba",
      "commits": 1846,
      "avatar": "https://avatars.githubusercontent.com/u/1657201?u=f611cc31b526fcfce560cc3cf5f2d8a8a47fd227&v=4&s=40"
    },
    {
      "rank": 16,
      "username": "soufianeessarhir",
      "realname": "سفيان الصغير",
      "profile": "https://github.com/soufianeessarhir",
      "commits": 1839,
      "avatar": "https://avatars.githubusercontent.com/u/96819427?u=c7015bc13f8aa4280396b7beb62c1126866d2a3e&v=4&s=40"
    },
    {
      "rank": 17,
      "username": "ayagmar",
      "realname": "Abdeslam Yassine Agmar",
      "profile": "https://github.com/ayagmar",
      "commits": 1746,
      "avatar": "https://avatars.githubusercontent.com/u/62888618?u=4df90f5a119f242055b5824453212d526990527a&v=4&s=40"
    },
    {
      "rank": 18,
      "username": "kill-ux",
      "realname": "Mustapha Boutoub",
      "profile": "https://github.com/kill-ux",
      "commits": 1720,
      "avatar": "https://avatars.githubusercontent.com/u/185858933?u=64b0fc36fa620dc22eb507a8c3674568f39fb216&v=4&s=40"
    },
    {
      "rank": 19,
      "username": "AhmedBaid",
      "realname": "AhmedBaid",
      "profile": "https://github.com/AhmedBaid",
      "commits": 1659,
      "avatar": "https://avatars.githubusercontent.com/u/150438476?u=2c8eb18abc433167f77ae21536f4d791e8d97ffa&v=4&s=40"
    },
    {
      "rank": 20,
      "username": "ayoub-ahnaou",
      "realname": "ayoub ahnaou",
      "profile": "https://github.com/ayoub-ahnaou",
      "commits": 1639,
      "avatar": "https://avatars.githubusercontent.com/u/180229018?u=178ab7da0b09abf0fc19f2c2a2f3a1732466b757&v=4&s=40"
    },
    {
      "rank": 21,
      "username": "iib0011",
      "realname": "Ibrahima G. Coulibaly",
      "profile": "https://github.com/iib0011",
      "commits": 1514,
      "avatar": "https://avatars.githubusercontent.com/u/58892076?u=3976d6faf235b6962094465bc761b7edc9cf37ef&v=4&s=40"
    },
    {
      "rank": 22,
      "username": "chaqchase",
      "realname": "Mohamed Achaq",
      "profile": "https://github.com/chaqchase",
      "commits": 1360,
      "avatar": "https://avatars.githubusercontent.com/u/92867709?u=1f5e67d9cf0f2d57fbf1939d60fba056e44ca8c6&v=4&s=40"
    },
    {
      "rank": 23,
      "username": "zakarialaoui10",
      "realname": "ZAKARIA ELALAOUI",
      "profile": "https://github.com/zakarialaoui10",
      "commits": 1321,
      "avatar": "https://avatars.githubusercontent.com/u/63521765?u=462cb75b34437bba775f9847e1beae52d0d9102a&v=4&s=40"
    },
    {
      "rank": 24,
      "username": "Douirat",
      "realname": "Bennacer Douirat",
      "profile": "https://github.com/Douirat",
      "commits": 1286,
      "avatar": "https://avatars.githubusercontent.com/u/150545510?u=b2efd77b65d1180f94df529408dfd12773fda0e2&v=4&s=40"
    },
    {
      "rank": 25,
      "username": "BenaliOssama",
      "realname": "OUSSAMA BENALI",
      "profile": "https://github.com/BenaliOssama",
      "commits": 1272,
      "avatar": "https://avatars.githubusercontent.com/u/121973489?u=8860abc1e8c0c7250d5411db492bb9d19aaac41a&v=4&s=40"
    },
    {
      "rank": 26,
      "username": "yelasri07",
      "realname": "Youssef El Asri",
      "profile": "https://github.com/yelasri07",
      "commits": 1225,
      "avatar": "https://avatars.githubusercontent.com/u/168789623?u=396e006afe696ee9210feb5ef588b91c9afcc23c&v=4&s=40"
    },
    {
      "rank": 27,
      "username": "CharrafiMed",
      "realname": "MOHAMED CHARRAFI",
      "profile": "https://github.com/CharrafiMed",
      "commits": 1222,
      "avatar": "https://avatars.githubusercontent.com/u/130717329?v=4&s=40"
    },
    {
      "rank": 28,
      "username": "SalimM21",
      "realname": "Salim-Majide",
      "profile": "https://github.com/SalimM21",
      "commits": 1185,
      "avatar": "https://avatars.githubusercontent.com/u/218786543?u=27eced3ffca86f3351631e3f8bb4027dbbc742d4&v=4&s=40"
    },
    {
      "rank": 29,
      "username": "moughamir",
      "realname": "Mohamed Moughamir",
      "profile": "https://github.com/moughamir",
      "commits": 1153,
      "avatar": "https://avatars.githubusercontent.com/u/8163598?u=0f7c5bcd2881f45a6109187182cd81265ef9d2f0&v=4&s=40"
    },
    {
      "rank": 30,
      "username": "RedaAz07",
      "realname": "Anniz Reda",
      "profile": "https://github.com/RedaAz07",
      "commits": 1045,
      "avatar": "https://avatars.githubusercontent.com/u/128867123?u=696c2c37b3d04b9ba938fd3bf910bf36b17bf027&v=4&s=40"
    },
    {
      "rank": 31,
      "username": "kardasch404",
      "realname": "Kardache Zakaria",
      "profile": "https://github.com/kardasch404",
      "commits": 1016,
      "avatar": "https://avatars.githubusercontent.com/u/89345718?u=52ba1926092e19401a249192315c3220b49211a3&v=4&s=40"
    },
    {
      "rank": 32,
      "username": "codehass",
      "realname": "Hassan EL OUARDY",
      "profile": "https://github.com/codehass",
      "commits": 1004,
      "avatar": "https://avatars.githubusercontent.com/u/92850366?u=ff1f4fc5cb3f3743a0c01b95dcbe250ef628600c&v=4&s=40"
    },
    {
      "rank": 33,
      "username": "saljaoui",
      "realname": "Soufian ALJAOUI",
      "profile": "https://github.com/saljaoui",
      "commits": 996,
      "avatar": "https://avatars.githubusercontent.com/u/161062883?u=4d3ae5f5d5cdf386d25b7eb0b6e56b7efbd3a685&v=4&s=40"
    },
    {
      "rank": 34,
      "username": "eoussama",
      "realname": "Oussama Essamadi",
      "profile": "https://github.com/eoussama",
      "commits": 976,
      "avatar": "https://avatars.githubusercontent.com/u/22644543?u=8fdbb9e4aa6918df8f7b23185bb26e861178eea5&v=4&s=40"
    },
    {
      "rank": 35,
      "username": "aminelebrini",
      "realname": "AMINE LEBRINI",
      "profile": "https://github.com/aminelebrini",
      "commits": 968,
      "avatar": "https://avatars.githubusercontent.com/u/113290995?u=3a109bb4fdde1b31d124da8872f092a822b9dc27&v=4&s=40"
    },
    {
      "rank": 36,
      "username": "ahmedbenkrarayc",
      "realname": "Ahmed Benkrara",
      "profile": "https://github.com/ahmedbenkrarayc",
      "commits": 958,
      "avatar": "https://avatars.githubusercontent.com/u/180205931?u=0c2fc296b6c1d4150a53c6e2e5e8606702f7035e&v=4&s=40"
    },
    {
      "rank": 37,
      "username": "hmaach",
      "realname": "Hamza Maach",
      "profile": "https://github.com/hmaach",
      "commits": 926,
      "avatar": "https://avatars.githubusercontent.com/u/103060222?u=a5730ea828b0bae7226d5e71cfe44af89d80be13&v=4&s=40"
    },
    {
      "rank": 38,
      "username": "hyper-ayoub",
      "realname": "ayoub bouagna",
      "profile": "https://github.com/hyper-ayoub",
      "commits": 883,
      "avatar": "https://avatars.githubusercontent.com/u/133155846?u=e5d497ef5ffe0e91158391f83e2ab952cb6998ab&v=4&s=40"
    },
    {
      "rank": 39,
      "username": "sounny",
      "realname": "sounny",
      "profile": "https://github.com/sounny",
      "commits": 873,
      "avatar": "https://avatars.githubusercontent.com/u/18355391?u=252abdb5ca627f2f9471443f30f4463eb75be019&v=4&s=40"
    },
    {
      "rank": 40,
      "username": "yezz123",
      "realname": "Yasser Tahiri",
      "profile": "https://github.com/yezz123",
      "commits": 843,
      "avatar": "https://avatars.githubusercontent.com/u/52716203?u=21b53ce4115062b1e20cb513e64ca0000c2ef127&v=4&s=40"
    },
    {
      "rank": 41,
      "username": "abdessamadelouarrag",
      "realname": "Abdessamad El Ouarrag",
      "profile": "https://github.com/abdessamadelouarrag",
      "commits": 813,
      "avatar": "https://avatars.githubusercontent.com/u/229820272?u=9d9e9e464cfd41f49bd6338d35d52a75e1b11164&v=4&s=40"
    },
    {
      "rank": 42,
      "username": "Abdellah-Bounafaa",
      "realname": "BOUNAFAA ABDELLAH",
      "profile": "https://github.com/Abdellah-Bounafaa",
      "commits": 800,
      "avatar": "https://avatars.githubusercontent.com/u/97734042?u=384f24e3761a962068d21787f54b2d65ce968a0d&v=4&s=40"
    },
    {
      "rank": 43,
      "username": "imedly",
      "realname": "El. Id.",
      "profile": "https://github.com/imedly",
      "commits": 793,
      "avatar": "https://avatars.githubusercontent.com/u/19668275?u=47ebf9b396140cde05bd716d30ac606219fdbe79&v=4&s=40"
    },
    {
      "rank": 44,
      "username": "Abdelilah-99",
      "realname": "Abdelilah Bouchikhi",
      "profile": "https://github.com/Abdelilah-99",
      "commits": 793,
      "avatar": "https://avatars.githubusercontent.com/u/125512577?u=c7c9ee9922775d03912c4415564c51be7e9e8817&v=4&s=40"
    },
    {
      "rank": 45,
      "username": "ismailsayen",
      "realname": "isayen",
      "profile": "https://github.com/ismailsayen",
      "commits": 790,
      "avatar": "https://avatars.githubusercontent.com/u/149976248?u=df9355bacfb1d0524ad1e83af8078960825f5d1c&v=4&s=40"
    },
    {
      "rank": 46,
      "username": "helouazizi",
      "realname": "Hassan El ouazizi",
      "profile": "https://github.com/helouazizi",
      "commits": 782,
      "avatar": "https://avatars.githubusercontent.com/u/158299018?u=02a36d1f826941f28020ced7170d8e6225128b5f&v=4&s=40"
    },
    {
      "rank": 47,
      "username": "mohammedhrima",
      "realname": "mohammed hrima",
      "profile": "https://github.com/mohammedhrima",
      "commits": 768,
      "avatar": "https://avatars.githubusercontent.com/u/71414472?u=1e5bf9560f2d432c8fc1cce93e28ef5ef0d275f3&v=4&s=40"
    },
    {
      "rank": 48,
      "username": "aminehabchi",
      "realname": "amine habchi",
      "profile": "https://github.com/aminehabchi",
      "commits": 754,
      "avatar": "https://avatars.githubusercontent.com/u/104910967?u=61e22bc59e5266965d7cea28afb15029b471c1e1&v=4&s=40"
    },
    {
      "rank": 49,
      "username": "SaidaAourras",
      "realname": "Saida Aourras",
      "profile": "https://github.com/SaidaAourras",
      "commits": 748,
      "avatar": "https://avatars.githubusercontent.com/u/126249145?u=c309091a64aceabef9304026b9bbea1bd48ce2b4&v=4&s=40"
    },
    {
      "rank": 50,
      "username": "aarab-abderrahmane",
      "realname": "abdulrahman",
      "profile": "https://github.com/aarab-abderrahmane",
      "commits": 743,
      "avatar": "https://avatars.githubusercontent.com/u/185629273?u=a39b1beb0caea05b9568e5b7646c92546b354936&v=4&s=40"
    },
    {
      "rank": 51,
      "username": "ibrahimoxx",
      "realname": "STOURI Ibrahim",
      "profile": "https://github.com/ibrahimoxx",
      "commits": 707,
      "avatar": "https://avatars.githubusercontent.com/u/171987819?u=f46b9d5703b0c6999e3c2cb44b8e7988b8f0723c&v=4&s=40"
    },
    {
      "rank": 52,
      "username": "BouglaceMarouane",
      "realname": "Marouane Bouglace",
      "profile": "https://github.com/BouglaceMarouane",
      "commits": 704,
      "avatar": "https://avatars.githubusercontent.com/u/190136999?u=b299f8093dde05bc4962243684e824913feca878&v=4&s=40"
    },
    {
      "rank": 53,
      "username": "ELMACHHOUNE",
      "realname": "MOHAMED EL MACHHOUNE",
      "profile": "https://github.com/ELMACHHOUNE",
      "commits": 677,
      "avatar": "https://avatars.githubusercontent.com/u/91902222?u=bc45dfdf378c0a82aa1c750429d678dd5bb07181&v=4&s=40"
    },
    {
      "rank": 54,
      "username": "e-aub",
      "realname": "Ayoub El Haddad",
      "profile": "https://github.com/e-aub",
      "commits": 669,
      "avatar": "https://avatars.githubusercontent.com/u/148923257?u=1ba8e34956632c181af7102a013c7c7d3228c228&v=4&s=40"
    },
    {
      "rank": 55,
      "username": "HamzaOutayb",
      "profile": "https://github.com/HamzaOutayb",
      "commits": 645,
      "avatar": "https://avatars.githubusercontent.com/u/169452213?v=4&s=40"
    },
    {
      "rank": 56,
      "username": "madaghaxx",
      "realname": "madagha",
      "profile": "https://github.com/madaghaxx",
      "commits": 630,
      "avatar": "https://avatars.githubusercontent.com/u/158001949?u=f7dc5fbf6d541b497e85a9c53673127ea2eb236b&v=4&s=40"
    },
    {
      "rank": 57,
      "username": "aallamaa",
      "realname": "Abdelkader ALLAM",
      "profile": "https://github.com/aallamaa",
      "commits": 625,
      "avatar": "https://avatars.githubusercontent.com/u/451799?v=4&s=40"
    },
    {
      "rank": 58,
      "username": "yassine-20042004",
      "realname": "Yassine Janane",
      "profile": "https://github.com/yassine-20042004",
      "commits": 620,
      "avatar": "https://avatars.githubusercontent.com/u/93791642?u=0d0b327ca90dc15a516bd2a9af08c7d198f541c5&v=4&s=40"
    },
    {
      "rank": 59,
      "username": "YusufLisawi",
      "realname": "Youssef El Aissaoui",
      "profile": "https://github.com/YusufLisawi",
      "commits": 616,
      "avatar": "https://avatars.githubusercontent.com/u/90868691?u=ec474f04211d337352f86c427c7642a627f5e605&v=4&s=40"
    },
    {
      "rank": 60,
      "username": "harunnoir",
      "realname": "𝗛𝗔𝗥𝗨𝗡 Noir",
      "profile": "https://github.com/harunnoir",
      "commits": 613,
      "avatar": "https://avatars.githubusercontent.com/u/152083466?u=85f9b03bcedf5ffbf4fc3a17a5e01d468f9a3041&v=4&s=40"
    },
    {
      "rank": 61,
      "username": "awbx",
      "realname": "Abdelhadi Sabani",
      "profile": "https://github.com/awbx",
      "commits": 609,
      "avatar": "https://avatars.githubusercontent.com/u/33328081?u=eb84599f4910bdb35a3d2a87f718a2eaeeeda7ff&v=4&s=40"
    },
    {
      "rank": 62,
      "username": "Zakarialabib",
      "realname": "Zakaria Labib",
      "profile": "https://github.com/Zakarialabib",
      "commits": 592,
      "avatar": "https://avatars.githubusercontent.com/u/58374576?u=9af659f0397cae16a4a9b58c16adb28dd966a409&v=4&s=40"
    },
    {
      "rank": 63,
      "username": "oldvibe",
      "realname": "yasyn nait edderhm",
      "profile": "https://github.com/oldvibe",
      "commits": 583,
      "avatar": "https://avatars.githubusercontent.com/u/135625795?u=32a104ad58cd9e31c376f79aefff95dbd367c4b5&v=4&s=40"
    },
    {
      "rank": 64,
      "username": "AbdelilahOu",
      "realname": "Ar7al",
      "profile": "https://github.com/AbdelilahOu",
      "commits": 569,
      "avatar": "https://avatars.githubusercontent.com/u/86406783?u=555940b327fd9383488841a423e7fabbe05b846a&v=4&s=40"
    },
    {
      "rank": 65,
      "username": "AnasImloul",
      "realname": "Anas Imloul",
      "profile": "https://github.com/AnasImloul",
      "commits": 565,
      "avatar": "https://avatars.githubusercontent.com/u/76872415?u=71899b895a19d90ae8575b8858ec239479df592f&v=4&s=40"
    },
    {
      "rank": 66,
      "username": "nissrine-elmniai",
      "realname": "Nissrine EL MNIAI",
      "profile": "https://github.com/nissrine-elmniai",
      "commits": 564,
      "avatar": "https://avatars.githubusercontent.com/u/191699345?u=8ad5a0565108893e3190e6650541e4fd38f63618&v=4&s=40"
    },
    {
      "rank": 67,
      "username": "uma-oo",
      "realname": "ooumayma",
      "profile": "https://github.com/uma-oo",
      "commits": 552,
      "avatar": "https://avatars.githubusercontent.com/u/76720983?u=e5541a3109fb0c39b0246445f4fb094879c0af66&v=4&s=40"
    },
    {
      "rank": 68,
      "username": "KingFrostii",
      "realname": "❄𝕱𝖗𝖔𝖘𝖙𝖎𝖎❄",
      "profile": "https://github.com/KingFrostii",
      "commits": 533,
      "avatar": "https://avatars.githubusercontent.com/u/289182268?u=d61069d5bd3176cb8113dda5110dd58f804388e7&v=4&s=40"
    },
    {
      "rank": 69,
      "username": "Safae26",
      "realname": "Safae",
      "profile": "https://github.com/Safae26",
      "commits": 526,
      "avatar": "https://avatars.githubusercontent.com/u/149904770?u=2e9157d6ff6f19eda89590a9843b0aeea8a866ec&v=4&s=40"
    },
    {
      "rank": 70,
      "username": "fihry",
      "realname": "MOHAMED EL FIHRY",
      "profile": "https://github.com/fihry",
      "commits": 526,
      "avatar": "https://avatars.githubusercontent.com/u/83623752?u=c3d246290debc6769ffd5f6d41b43880446a2d98&v=4&s=40"
    },
    {
      "rank": 71,
      "username": "3zden",
      "realname": "3zden",
      "profile": "https://github.com/3zden",
      "commits": 521,
      "avatar": "https://avatars.githubusercontent.com/u/184450428?u=a4e402a9bc05ccf412df54e8e9485353fe5c7953&v=4&s=40"
    },
    {
      "rank": 72,
      "username": "AyoubOutrgua",
      "realname": "Ayoub Outrgua",
      "profile": "https://github.com/AyoubOutrgua",
      "commits": 517,
      "avatar": "https://avatars.githubusercontent.com/u/74433630?u=f1264dd27529179c8929379ec160d4454776f9d9&v=4&s=40"
    },
    {
      "rank": 73,
      "username": "ababdelo",
      "realname": "Abderrahmane Abdelouafi",
      "profile": "https://github.com/ababdelo",
      "commits": 516,
      "avatar": "https://avatars.githubusercontent.com/u/118723356?u=b136501e7fa58bb846de0ac8546402eb278ba7bd&v=4&s=40"
    },
    {
      "rank": 74,
      "username": "afrabouzehar",
      "realname": "Afra BOUZEHAR",
      "profile": "https://github.com/afrabouzehar",
      "commits": 512,
      "avatar": "https://avatars.githubusercontent.com/u/241137953?u=570bca4c513c479b1b8e4e00571565abec6cb99d&v=4&s=40"
    },
    {
      "rank": 75,
      "username": "Ayoub-Benramdane",
      "realname": "Ayoub Benrmadane",
      "profile": "https://github.com/Ayoub-Benramdane",
      "commits": 507,
      "avatar": "https://avatars.githubusercontent.com/u/145620173?u=277e659339f5e41387f882afabf6e629c7bc0f22&v=4&s=40"
    },
    {
      "rank": 76,
      "username": "mdbentaleb",
      "realname": "Mohamed Bentaleb",
      "profile": "https://github.com/mdbentaleb",
      "commits": 495,
      "avatar": "https://avatars.githubusercontent.com/u/132714803?u=b64f9107d76470559b4f5579927f7a9978048fd5&v=4&s=40"
    },
    {
      "rank": 77,
      "username": "idmossab",
      "realname": "Idbenkellal Mossab",
      "profile": "https://github.com/idmossab",
      "commits": 488,
      "avatar": "https://avatars.githubusercontent.com/u/64993848?u=3de2ad7e957a2f131b4e161a07cf641d7b3e2d93&v=4&s=40"
    },
    {
      "rank": 78,
      "username": "AymaneMehdi",
      "realname": "Aymane Mehdi",
      "profile": "https://github.com/AymaneMehdi",
      "commits": 487,
      "avatar": "https://avatars.githubusercontent.com/u/119676798?u=acdd0cac220bf01c4a6c84d8d4337b27b608f6ee&v=4&s=40"
    },
    {
      "rank": 79,
      "username": "YOUSSEFLJ9",
      "realname": "youssef momen",
      "profile": "https://github.com/YOUSSEFLJ9",
      "commits": 485,
      "avatar": "https://avatars.githubusercontent.com/u/125615450?u=95423a8e9ceb6bd14d173b0b2921975b1cd5775c&v=4&s=40"
    },
    {
      "rank": 80,
      "username": "3manuel0",
      "realname": "3manuel",
      "profile": "https://github.com/3manuel0",
      "commits": 484,
      "avatar": "https://avatars.githubusercontent.com/u/101729406?u=f1b07aa1043ec21ef56a32076ed891dfeb1891f6&v=4&s=40"
    },
    {
      "rank": 81,
      "username": "AmraniCh",
      "realname": "Shakir El Amrani",
      "profile": "https://github.com/AmraniCh",
      "commits": 476,
      "avatar": "https://avatars.githubusercontent.com/u/49124992?u=6002db3716a724e6fc45ab1c91606bee63cc8609&v=4&s=40"
    },
    {
      "rank": 82,
      "username": "Abdellahsyani",
      "realname": "Abdellah",
      "profile": "https://github.com/Abdellahsyani",
      "commits": 474,
      "avatar": "https://avatars.githubusercontent.com/u/133210126?u=d131c98a6b8d86137c3644cb8f47e7185669b898&v=4&s=40"
    },
    {
      "rank": 83,
      "username": "elbachir-one",
      "realname": "El Bachir",
      "profile": "https://github.com/elbachir-one",
      "commits": 460,
      "avatar": "https://avatars.githubusercontent.com/u/28448503?u=ba762b20e01161640d960ea3240283dd19c24aea&v=4&s=40"
    },
    {
      "rank": 84,
      "username": "ioulasri",
      "realname": "ioulasri",
      "profile": "https://github.com/ioulasri",
      "commits": 451,
      "avatar": "https://avatars.githubusercontent.com/u/115421891?u=8bf310da7e9c9003c130ea590fc23faa5107e128&v=4&s=40"
    },
    {
      "rank": 85,
      "username": "faissaloux",
      "realname": "Faissal Wahabali",
      "profile": "https://github.com/faissaloux",
      "commits": 446,
      "avatar": "https://avatars.githubusercontent.com/u/60013703?u=62aab13e7ad1325ef185585cf2478fdf84ba4c20&v=4&s=40"
    },
    {
      "rank": 86,
      "username": "Jakiboy",
      "realname": "Jakiboy",
      "profile": "https://github.com/Jakiboy",
      "commits": 443,
      "avatar": "https://avatars.githubusercontent.com/u/7604550?u=5e3bab195511915883aef73502f19cf016faa918&v=4&s=40"
    },
    {
      "rank": 87,
      "username": "heisenstack",
      "realname": "Mohamed Amine Dinani",
      "profile": "https://github.com/heisenstack",
      "commits": 437,
      "avatar": "https://avatars.githubusercontent.com/u/211218872?u=0fb973de36f17252e4c1214ce7c50b3c87ef2e4b&v=4&s=40"
    },
    {
      "rank": 88,
      "username": "madanimkhitar22-beep",
      "realname": "El Madani El mkhitar (madani004",
      "profile": "https://github.com/madanimkhitar22-beep",
      "commits": 430,
      "avatar": "https://avatars.githubusercontent.com/u/228516289?u=f3f06e39d29e8f29e2a0a30bcb1455786a90765a&v=4&s=40"
    },
    {
      "rank": 89,
      "username": "yassnemo",
      "realname": "Yassine Erradouani",
      "profile": "https://github.com/yassnemo",
      "commits": 426,
      "avatar": "https://avatars.githubusercontent.com/u/97001899?u=49546ea263e4698264677a37859240272a3ab333&v=4&s=40"
    },
    {
      "rank": 90,
      "username": "yel-hadd",
      "realname": "Yassine El Haddad",
      "profile": "https://github.com/yel-hadd",
      "commits": 417,
      "avatar": "https://avatars.githubusercontent.com/u/82560247?u=2a1427524febc0d0d3f2427bbb30d6b447d8b0ff&v=4&s=40"
    },
    {
      "rank": 91,
      "username": "KanekiEzz",
      "realname": "! 𝕜𝕒𝕟𝕖𝕜𝕚 | かねき ⚡",
      "profile": "https://github.com/KanekiEzz",
      "commits": 415,
      "avatar": "https://avatars.githubusercontent.com/u/110631781?u=87bfe5cba015c8f560cbd2360a6f571f11cb04a2&v=4&s=40"
    },
    {
      "rank": 92,
      "username": "marstrx",
      "realname": "Marouane Bachar",
      "profile": "https://github.com/marstrx",
      "commits": 410,
      "avatar": "https://avatars.githubusercontent.com/u/169992204?u=977af0f23e32736c91132d6475770fc742b74b94&v=4&s=40"
    },
    {
      "rank": 93,
      "username": "reblox01",
      "realname": "0x8D",
      "profile": "https://github.com/reblox01",
      "commits": 402,
      "avatar": "https://avatars.githubusercontent.com/u/74146687?u=d7e1608dd3a8aa67f959c630792c8be9e640d349&v=4&s=40"
    },
    {
      "rank": 94,
      "username": "SegMind25",
      "realname": "Bekkali",
      "profile": "https://github.com/SegMind25",
      "commits": 401,
      "avatar": "https://avatars.githubusercontent.com/u/209148644?u=e8f411a89df800d2eb8d1f308c469c4a5b42ff90&v=4&s=40"
    },
    {
      "rank": 95,
      "username": "yassernamez03",
      "realname": "Yasser Namez",
      "profile": "https://github.com/yassernamez03",
      "commits": 400,
      "avatar": "https://avatars.githubusercontent.com/u/99099773?u=4dc1488ed45ba68190f418484b36b3c7fe4ba938&v=4&s=40"
    },
    {
      "rank": 96,
      "username": "heyZakaria",
      "realname": "Zakaria Abdelali",
      "profile": "https://github.com/heyZakaria",
      "commits": 400,
      "avatar": "https://avatars.githubusercontent.com/u/104455697?u=3a0ceacd8382e96fe4214f611209f50ec08c9b79&v=4&s=40"
    },
    {
      "rank": 97,
      "username": "s-shemmee",
      "realname": "shemmee.codes",
      "profile": "https://github.com/s-shemmee",
      "commits": 396,
      "avatar": "https://avatars.githubusercontent.com/u/56132945?u=9df2c89c914c9d0d28ca33453a482e7b231feda6&v=4&s=40"
    },
    {
      "rank": 98,
      "username": "achahid19",
      "realname": "anas chahid ksabi",
      "profile": "https://github.com/achahid19",
      "commits": 389,
      "avatar": "https://avatars.githubusercontent.com/u/125438524?u=c9e7812a88c0e945ca485d73239fdbc33ed4ebc6&v=4&s=40"
    },
    {
      "rank": 99,
      "username": "rachid-serraf",
      "realname": "Rachid Serraf",
      "profile": "https://github.com/rachid-serraf",
      "commits": 372,
      "avatar": "https://avatars.githubusercontent.com/u/127261478?u=25c3eed06f96db784a7ed0f1ce0239ed07dfff02&v=4&s=40"
    },
    {
      "rank": 100,
      "username": "HMZElidrissi",
      "realname": "Hamza El Idrissi",
      "profile": "https://github.com/HMZElidrissi",
      "commits": 371,
      "avatar": "https://avatars.githubusercontent.com/u/114808070?u=8ba18dc57c68acd12c3b90e269b65e238555282e&v=4&s=40"
    },
    {
      "rank": 101,
      "username": "roxm337",
      "realname": "r10xM37",
      "profile": "https://github.com/roxm337",
      "commits": 369,
      "avatar": "https://avatars.githubusercontent.com/u/53299920?u=25dafd84579572f14cba6b15488cb435a9b225c2&v=4&s=40"
    },
    {
      "rank": 102,
      "username": "hafidaso",
      "realname": "Hafida Belayd",
      "profile": "https://github.com/hafidaso",
      "commits": 363,
      "avatar": "https://avatars.githubusercontent.com/u/49368062?u=8ab18c2c6d7e647c04c6929fdbe83e3555982a27&v=4&s=40"
    },
    {
      "rank": 103,
      "username": "YahyaSaadaoui",
      "realname": "Yahya saadaoui",
      "profile": "https://github.com/YahyaSaadaoui",
      "commits": 363,
      "avatar": "https://avatars.githubusercontent.com/u/99345333?u=5708acb5611e611576c4b7c4a509761b079ada4d&v=4&s=40"
    },
    {
      "rank": 104,
      "username": "larbi-asmaoui",
      "realname": "Larbi ASMAOUI",
      "profile": "https://github.com/larbi-asmaoui",
      "commits": 362,
      "avatar": "https://avatars.githubusercontent.com/u/103370123?u=fdc5c77d144def0dd9f7d448fd531543036f2d07&v=4&s=40"
    },
    {
      "rank": 105,
      "username": "raynlamlaika",
      "realname": "lamlaika rayane",
      "profile": "https://github.com/raynlamlaika",
      "commits": 362,
      "avatar": "https://avatars.githubusercontent.com/u/139387044?u=4ed4375338f005448416bb1c68e2b53c09ce39db&v=4&s=40"
    },
    {
      "rank": 106,
      "username": "louhabali",
      "realname": "louhab ali",
      "profile": "https://github.com/louhabali",
      "commits": 350,
      "avatar": "https://avatars.githubusercontent.com/u/128259921?u=8a4489dbb2061b2d8148ee7f9af1786022be0e31&v=4&s=40"
    },
    {
      "rank": 107,
      "username": "aliBenhenia",
      "realname": "Ali benhenia",
      "profile": "https://github.com/aliBenhenia",
      "commits": 337,
      "avatar": "https://avatars.githubusercontent.com/u/95689141?u=b01c77a4e8c1d959cfc4cb298e182e285d352f0a&v=4&s=40"
    },
    {
      "rank": 108,
      "username": "YOUSSEF-BT",
      "realname": "Youssef Bouzit",
      "profile": "https://github.com/YOUSSEF-BT",
      "commits": 335,
      "avatar": "https://avatars.githubusercontent.com/u/115832243?u=c716f841bd5f989a3e45dda03b7478857dee90e0&v=4&s=40"
    },
    {
      "rank": 109,
      "username": "EVBLOOD",
      "realname": "Saad AKLLAM",
      "profile": "https://github.com/EVBLOOD",
      "commits": 334,
      "avatar": "https://avatars.githubusercontent.com/u/63886515?u=a1cf4c160b16cf73a6b7168d4b9abb0e55dc41b6&v=4&s=40"
    },
    {
      "rank": 110,
      "username": "ysnbhb",
      "realname": "yassine bahbib",
      "profile": "https://github.com/ysnbhb",
      "commits": 328,
      "avatar": "https://avatars.githubusercontent.com/u/151177203?u=8f059254acc564ebfa663018d539bd02b25d71b8&v=4&s=40"
    },
    {
      "rank": 111,
      "username": "walidbosso",
      "realname": "Walid BOUSSOU",
      "profile": "https://github.com/walidbosso",
      "commits": 328,
      "avatar": "https://avatars.githubusercontent.com/u/121355412?u=d09c60c933ce8a8cc89439fad7a10765dcac1c84&v=4&s=40"
    },
    {
      "rank": 112,
      "username": "abdelkabirouadoukou",
      "realname": "Abdelkabir Ouadoukou",
      "profile": "https://github.com/abdelkabirouadoukou",
      "commits": 328,
      "avatar": "https://avatars.githubusercontent.com/u/152230716?u=60bb48b59a338758cc721c3b9aa4cffc3bed93c3&v=4&s=40"
    },
    {
      "rank": 113,
      "username": "x3alone",
      "realname": "otman chouari",
      "profile": "https://github.com/x3alone",
      "commits": 326,
      "avatar": "https://avatars.githubusercontent.com/u/111086385?u=306c5fe9b57227c7f24d5983f804f23797cb26e0&v=4&s=40"
    },
    {
      "rank": 114,
      "username": "Ysen1903",
      "realname": "Ennaya Yassine",
      "profile": "https://github.com/Ysen1903",
      "commits": 325,
      "avatar": "https://avatars.githubusercontent.com/u/128385979?u=919b011e45ba9281a80b4f185986e3538ad097c7&v=4&s=40"
    },
    {
      "rank": 115,
      "username": "A-fethi",
      "realname": "FETHI Abderrahmane",
      "profile": "https://github.com/A-fethi",
      "commits": 323,
      "avatar": "https://avatars.githubusercontent.com/u/95975702?u=ca566460f234ba7e4f1150f926cc7bdd5dd8530f&v=4&s=40"
    },
    {
      "rank": 116,
      "username": "RachidNaitSaid2002",
      "realname": "Rachid Nait Said",
      "profile": "https://github.com/RachidNaitSaid2002",
      "commits": 323,
      "avatar": "https://avatars.githubusercontent.com/u/154028066?u=f977d4f985006d468d7197bbc17ea10c3db0ef69&v=4&s=40"
    },
    {
      "rank": 117,
      "username": "TAnas0",
      "realname": "Anas TIOUR",
      "profile": "https://github.com/TAnas0",
      "commits": 323,
      "avatar": "https://avatars.githubusercontent.com/u/12121506?u=f35d3fd64d0e223a3c5f37f0696257485b335a75&v=4&s=40"
    },
    {
      "rank": 118,
      "username": "samir-elasri",
      "realname": "Samir El Asri",
      "profile": "https://github.com/samir-elasri",
      "commits": 320,
      "avatar": "https://avatars.githubusercontent.com/u/37915947?u=998c18c3776c7a355274bb4829543d7f457b3320&v=4&s=40"
    },
    {
      "rank": 119,
      "username": "0xm3d",
      "realname": "Mohamed BOUHADI",
      "profile": "https://github.com/0xm3d",
      "commits": 319,
      "avatar": "https://avatars.githubusercontent.com/u/174951240?u=662bf04ff1b4550b038c95fd370d2e8c59034bd7&v=4&s=40"
    },
    {
      "rank": 120,
      "username": "Ybouali",
      "realname": "Yassine Bouali",
      "profile": "https://github.com/Ybouali",
      "commits": 314,
      "avatar": "https://avatars.githubusercontent.com/u/89746106?u=fd1b1574bd20fe8b2a5e976350a36813f1794512&v=4&s=40"
    },
    {
      "rank": 121,
      "username": "Ayouub-aj",
      "realname": "Ayouub_aj",
      "profile": "https://github.com/Ayouub-aj",
      "commits": 312,
      "avatar": "https://avatars.githubusercontent.com/u/87580381?u=eedff6331e5e92189e3337191025da13f9e5cf8f&v=4&s=40"
    },
    {
      "rank": 122,
      "username": "Lekssays",
      "realname": "Ahmed Lekssays",
      "profile": "https://github.com/Lekssays",
      "commits": 310,
      "avatar": "https://avatars.githubusercontent.com/u/5169661?u=1b95a4cb34a3c357f3e21969d2a983e3dd3cddf7&v=4&s=40"
    },
    {
      "rank": 123,
      "username": "LUZAmaxxp",
      "realname": "Ayman ALLOUCH",
      "profile": "https://github.com/LUZAmaxxp",
      "commits": 309,
      "avatar": "https://avatars.githubusercontent.com/u/140757412?u=783ff639731cc764ccd9f6871c8883c25756f730&v=4&s=40"
    },
    {
      "rank": 124,
      "username": "jbajady",
      "realname": "👨‍💻 jamal bajady",
      "profile": "https://github.com/jbajady",
      "commits": 309,
      "avatar": "https://avatars.githubusercontent.com/u/167723468?u=f48ca7b27059549a8d5bdcfec6adff94483bb4d6&v=4&s=40"
    },
    {
      "rank": 125,
      "username": "mar1shell",
      "realname": "EL-HAMDAOUI MAROUANE",
      "profile": "https://github.com/mar1shell",
      "commits": 301,
      "avatar": "https://avatars.githubusercontent.com/u/114416183?u=2e48a03bddc6b0e8ab2c79c4f9e64ce897d8a908&v=4&s=40"
    },
    {
      "rank": 126,
      "username": "khafifithebork",
      "realname": "Ayman Khafifi",
      "profile": "https://github.com/khafifithebork",
      "commits": 300,
      "avatar": "https://avatars.githubusercontent.com/u/207626202?u=dbcf6e3983e68c6a3a98289f56a77ff789799bcc&v=4&s=40"
    },
    {
      "rank": 127,
      "username": "Reda-Ganoutre01",
      "realname": "Reda Ganoutre",
      "profile": "https://github.com/Reda-Ganoutre01",
      "commits": 299,
      "avatar": "https://avatars.githubusercontent.com/u/121640970?u=b9ab7d6a6862b3b7ca5532fc6346503b4bc3ded7&v=4&s=40"
    },
    {
      "rank": 128,
      "username": "MohamedOuijjane",
      "realname": "Mohamed OUIJJANE",
      "profile": "https://github.com/MohamedOuijjane",
      "commits": 298,
      "avatar": "https://avatars.githubusercontent.com/u/153356478?u=441b455685ae9928bd2f3ff3e716b8eb742eb911&v=4&s=40"
    },
    {
      "rank": 129,
      "username": "arharif",
      "realname": "Rharif Anass",
      "profile": "https://github.com/arharif",
      "commits": 298,
      "avatar": "https://avatars.githubusercontent.com/u/88338613?u=9d2e4637ae141a90b99bd60d614a97d1e0378eb6&v=4&s=40"
    },
    {
      "rank": 130,
      "username": "Sbeytour",
      "realname": "safae beytour",
      "profile": "https://github.com/Sbeytour",
      "commits": 297,
      "avatar": "https://avatars.githubusercontent.com/u/186501579?u=3683c5154475263b324bc38da4889eb62398810b&v=4&s=40"
    },
    {
      "rank": 131,
      "username": "BEAJousama",
      "realname": "BEAJ Ousama",
      "profile": "https://github.com/BEAJousama",
      "commits": 291,
      "avatar": "https://avatars.githubusercontent.com/u/48697722?u=109a0d1a3d234af8db8a611ff289c525f7e11b74&v=4&s=40"
    },
    {
      "rank": 132,
      "username": "aymaneelmaini",
      "realname": "Aymane El Maini",
      "profile": "https://github.com/aymaneelmaini",
      "commits": 289,
      "avatar": "https://avatars.githubusercontent.com/u/121185649?u=51ccacd3215240cada0b69b1d20bdde2f77e7c7a&v=4&s=40"
    },
    {
      "rank": 133,
      "username": "Mohamed-Moumni",
      "realname": "Mohamed Moumni",
      "profile": "https://github.com/Mohamed-Moumni",
      "commits": 283,
      "avatar": "https://avatars.githubusercontent.com/u/78799596?u=2363d931b53a6a7b4dd07a67534b6e21dfc3669d&v=4&s=40"
    },
    {
      "rank": 134,
      "username": "miller-203",
      "realname": "Youness Laidi",
      "profile": "https://github.com/miller-203",
      "commits": 270,
      "avatar": "https://avatars.githubusercontent.com/u/158384878?u=5e539748dad89dcf58a1e044b9a247bbf56e6dd6&v=4&s=40"
    },
    {
      "rank": 135,
      "username": "useit015",
      "realname": "Oussama Nahiz",
      "profile": "https://github.com/useit015",
      "commits": 269,
      "avatar": "https://avatars.githubusercontent.com/u/32947386?u=d2ddf838e00e231ec5b3c2d4dae20da25000ab59&v=4&s=40"
    },
    {
      "rank": 136,
      "username": "medyo",
      "realname": "Mehdi Sakout",
      "profile": "https://github.com/medyo",
      "commits": 268,
      "avatar": "https://avatars.githubusercontent.com/u/2389584?u=4bf4e58142d2233dac056f000ae19fedf46818b8&v=4&s=40"
    },
    {
      "rank": 137,
      "username": "simoz404",
      "realname": "BAKHOUCH MOHAMED",
      "profile": "https://github.com/simoz404",
      "commits": 268,
      "avatar": "https://avatars.githubusercontent.com/u/62752170?u=1dd2e19dc869f48dc62aec26bdbdd057df1a2c78&v=4&s=40"
    },
    {
      "rank": 138,
      "username": "WeismannS",
      "realname": "Weismann",
      "profile": "https://github.com/WeismannS",
      "commits": 268,
      "avatar": "https://avatars.githubusercontent.com/u/60429301?u=9d7c17530e83de9601da2fe61aa7807f6f5463c7&v=4&s=40"
    },
    {
      "rank": 139,
      "username": "samir-ouaammou",
      "realname": "Samir Ouaammou",
      "profile": "https://github.com/samir-ouaammou",
      "commits": 267,
      "avatar": "https://avatars.githubusercontent.com/u/182961248?u=64b0a902dc770a2ab4ba2467a751de217874e795&v=4&s=40"
    },
    {
      "rank": 140,
      "username": "Hamzaelghazouani1",
      "realname": "Hamza el Ghazouani",
      "profile": "https://github.com/Hamzaelghazouani1",
      "commits": 265,
      "avatar": "https://avatars.githubusercontent.com/u/91982044?u=1ff69cdd888da9df8cb1c73b3ed583d9b9fa8306&v=4&s=40"
    },
    {
      "rank": 141,
      "username": "ansezz",
      "realname": "Anass Ez-zouaine",
      "profile": "https://github.com/ansezz",
      "commits": 252,
      "avatar": "https://avatars.githubusercontent.com/u/8946258?u=4af6e0b71860e6f8487b10b1f1c745b95cd0f12a&v=4&s=40"
    },
    {
      "rank": 142,
      "username": "yjose",
      "realname": "Youssouf EL AZIZI",
      "profile": "https://github.com/yjose",
      "commits": 251,
      "avatar": "https://avatars.githubusercontent.com/u/11137944?u=0d5fcb71088fdee1ddb15ef177132993705c610c&v=4&s=40"
    },
    {
      "rank": 143,
      "username": "tantaouibahaa",
      "realname": "ryver",
      "profile": "https://github.com/tantaouibahaa",
      "commits": 249,
      "avatar": "https://avatars.githubusercontent.com/u/89860338?u=347817b0e16cc8d2ccdd933ac6c6eec012fa47fe&v=4&s=40"
    },
    {
      "rank": 144,
      "username": "PinkiePieExplosion",
      "realname": "Shepard!",
      "profile": "https://github.com/PinkiePieExplosion",
      "commits": 248,
      "avatar": "https://avatars.githubusercontent.com/u/251366603?u=915f6f55a58d3655f5328c685d8d51a7520375e0&v=4&s=40"
    },
    {
      "rank": 145,
      "username": "AnasFiguigui",
      "realname": "Anas",
      "profile": "https://github.com/AnasFiguigui",
      "commits": 248,
      "avatar": "https://avatars.githubusercontent.com/u/92400545?u=4ea2e786a8136c65b03314c2774aa0fbcfdcf4f0&v=4&s=40"
    },
    {
      "rank": 146,
      "username": "aarab-ayoub",
      "realname": "AYAARAB",
      "profile": "https://github.com/aarab-ayoub",
      "commits": 247,
      "avatar": "https://avatars.githubusercontent.com/u/112900657?u=05130158c8fdec386ef69a6a97f827ac8b3ffa15&v=4&s=40"
    },
    {
      "rank": 147,
      "username": "razaane",
      "realname": "WAKHIDI RAZANE",
      "profile": "https://github.com/razaane",
      "commits": 246,
      "avatar": "https://avatars.githubusercontent.com/u/125482268?u=3ccb6d67266cbb5148fb986032cbd8b7cc5a5e3f&v=4&s=40"
    },
    {
      "rank": 148,
      "username": "hel-mefe",
      "realname": "HichamElmefeddel",
      "profile": "https://github.com/hel-mefe",
      "commits": 242,
      "avatar": "https://avatars.githubusercontent.com/u/17704281?u=b018fd3bfc0003347451d16fdad37c813460a45d&v=4&s=40"
    },
    {
      "rank": 149,
      "username": "khalid21456",
      "realname": "KHALID EDAOUDI",
      "profile": "https://github.com/khalid21456",
      "commits": 242,
      "avatar": "https://avatars.githubusercontent.com/u/143753740?u=7cda6dbd0726c3607713cca2b67bcaa7dc37a516&v=4&s=40"
    },
    {
      "rank": 150,
      "username": "yahyaahs",
      "realname": "Yahya",
      "profile": "https://github.com/yahyaahs",
      "commits": 239,
      "avatar": "https://avatars.githubusercontent.com/u/83820962?u=53cc639b2ca44a0606cc86643bbcfbc5bd9fcf7d&v=4&s=40"
    },
    {
      "rank": 151,
      "username": "safoinme",
      "realname": "Safoine El Khabich",
      "profile": "https://github.com/safoinme",
      "commits": 237,
      "avatar": "https://avatars.githubusercontent.com/u/34200873?u=e2ba79155f0e85a2e31e1a705e38eeae8e428b28&v=4&s=40"
    },
    {
      "rank": 152,
      "username": "anasfik",
      "realname": "Anas Fikhi",
      "profile": "https://github.com/anasfik",
      "commits": 234,
      "avatar": "https://avatars.githubusercontent.com/u/25140579?u=77236e36899f1f7aa7afb799c98c4ce7ee154dc2&v=4&s=40"
    },
    {
      "rank": 153,
      "username": "badriyassine",
      "realname": "Yassine Badri",
      "profile": "https://github.com/badriyassine",
      "commits": 234,
      "avatar": "https://avatars.githubusercontent.com/u/199480332?u=e931657b48a8247c7987f788348124c4b526e493&v=4&s=40"
    },
    {
      "rank": 154,
      "username": "0thmanee",
      "realname": "Othmane BOUCHTA",
      "profile": "https://github.com/0thmanee",
      "commits": 233,
      "avatar": "https://avatars.githubusercontent.com/u/109211383?u=83860a9dc10168c6998b7565ee0d2d900a8479cf&v=4&s=40"
    },
    {
      "rank": 155,
      "username": "walid-zouguagh",
      "profile": "https://github.com/walid-zouguagh",
      "commits": 232,
      "avatar": "https://avatars.githubusercontent.com/u/166491264?u=feaae788f1e0d50392fcba0f49ef5cdf75eec2cc&v=4&s=40"
    },
    {
      "rank": 156,
      "username": "jaguar-ks",
      "realname": "Fahd",
      "profile": "https://github.com/jaguar-ks",
      "commits": 229,
      "avatar": "https://avatars.githubusercontent.com/u/99019879?u=d7823843210badf95b04789285b5f35cfaf2fa38&v=4&s=40"
    },
    {
      "rank": 157,
      "username": "Zizwar",
      "realname": "Ibrahim BIDI",
      "profile": "https://github.com/Zizwar",
      "commits": 227,
      "avatar": "https://avatars.githubusercontent.com/u/1431864?u=5a540e463e06c3238d820f5618882abaae15bc9a&v=4&s=40"
    },
    {
      "rank": 158,
      "username": "AmbitiousFlowDev",
      "realname": "Mohamed LAFROUH",
      "profile": "https://github.com/AmbitiousFlowDev",
      "commits": 224,
      "avatar": "https://avatars.githubusercontent.com/u/59917135?u=4b39d16f76ce7d269d117cd8827365e9d2f9b140&v=4&s=40"
    },
    {
      "rank": 159,
      "username": "mowgly11",
      "realname": "John",
      "profile": "https://github.com/mowgly11",
      "commits": 223,
      "avatar": "https://avatars.githubusercontent.com/u/83482871?u=997b332c059abca2591f51b12d47bab8ff162cdb&v=4&s=40"
    },
    {
      "rank": 160,
      "username": "zlayine",
      "realname": "Zouheir Layine",
      "profile": "https://github.com/zlayine",
      "commits": 222,
      "avatar": "https://avatars.githubusercontent.com/u/58786497?u=9068f5ee9dc71e1b3e7e9ac5774b6c6b36b24b23&v=4&s=40"
    },
    {
      "rank": 161,
      "username": "marouaneaddou",
      "realname": "Marouane Addou",
      "profile": "https://github.com/marouaneaddou",
      "commits": 219,
      "avatar": "https://avatars.githubusercontent.com/u/105064179?u=4bdbbe082c2f95cc437998b2353ee5d8b1ca2612&v=4&s=40"
    },
    {
      "rank": 162,
      "username": "khaldi-med",
      "realname": "Mohamed Khaldi",
      "profile": "https://github.com/khaldi-med",
      "commits": 219,
      "avatar": "https://avatars.githubusercontent.com/u/55020677?u=d813ea2c43d43fbb9eeb646f4c05b3d2a08a2bf8&v=4&s=40"
    },
    {
      "rank": 163,
      "username": "amineaith3",
      "realname": "sakuun_aah",
      "profile": "https://github.com/amineaith3",
      "commits": 217,
      "avatar": "https://avatars.githubusercontent.com/u/91127128?u=a3c10b1968e2bd66df242d82179f7d0ef36a52ac&v=4&s=40"
    },
    {
      "rank": 164,
      "username": "abdenassar01",
      "realname": "Abdenassar Amimi",
      "profile": "https://github.com/abdenassar01",
      "commits": 217,
      "avatar": "https://avatars.githubusercontent.com/u/78881740?u=e97334a19b55f2cc5e12bc334612024e391f0a99&v=4&s=40"
    },
    {
      "rank": 165,
      "username": "haddoumounir",
      "realname": "mounir",
      "profile": "https://github.com/haddoumounir",
      "commits": 213,
      "avatar": "https://avatars.githubusercontent.com/u/165167690?u=e002c7cfd9c036577bd61d2dca14d1eae1ef8c70&v=4&s=40"
    },
    {
      "rank": 166,
      "username": "ozennou",
      "realname": "mohamed amine ozennou",
      "profile": "https://github.com/ozennou",
      "commits": 212,
      "avatar": "https://avatars.githubusercontent.com/u/102986762?u=4b3af1ff6ac2209aaa36978ee2a87c31d98483a3&v=4&s=40"
    },
    {
      "rank": 167,
      "username": "Ghanmidev2012",
      "realname": "Ghanmidev2012",
      "profile": "https://github.com/Ghanmidev2012",
      "commits": 211,
      "avatar": "https://avatars.githubusercontent.com/u/242857573?u=f57a205d93cf67b0407f5ba6bbfdfdaa5e5c9729&v=4&s=40"
    },
    {
      "rank": 168,
      "username": "midrissi",
      "realname": "IDRISSI Mohamed",
      "profile": "https://github.com/midrissi",
      "commits": 210,
      "avatar": "https://avatars.githubusercontent.com/u/3237344?u=664d6c27509ee0385894c19fe9a48cca6cb01608&v=4&s=40"
    },
    {
      "rank": 169,
      "username": "benjdiasaad",
      "realname": "Benjdia Saad",
      "profile": "https://github.com/benjdiasaad",
      "commits": 207,
      "avatar": "https://avatars.githubusercontent.com/u/58569768?u=78ee794086a2bbaa7e7f4a4ee16e8fcaa9830241&v=4&s=40"
    },
    {
      "rank": 170,
      "username": "SihamNafie24",
      "realname": "siham nafie",
      "profile": "https://github.com/SihamNafie24",
      "commits": 207,
      "avatar": "https://avatars.githubusercontent.com/u/169382018?u=ebdf2bb3759e82f295bd47b3f771ec65c30df3ef&v=4&s=40"
    },
    {
      "rank": 171,
      "username": "abdelhak-zaaim",
      "realname": "Abdelhak Zaaim",
      "profile": "https://github.com/abdelhak-zaaim",
      "commits": 205,
      "avatar": "https://avatars.githubusercontent.com/u/92628902?u=331f7433e4d3da8efd6b813e14bdce5133413c26&v=4&s=40"
    },
    {
      "rank": 172,
      "username": "hassankarrach",
      "realname": "Zero",
      "profile": "https://github.com/hassankarrach",
      "commits": 201,
      "avatar": "https://avatars.githubusercontent.com/u/80120118?u=99d62fdb1bd9e6657eae8e431121862c03e9a17e&v=4&s=40"
    },
    {
      "rank": 173,
      "username": "Liams-theCreator",
      "realname": "Liams-theCreator",
      "profile": "https://github.com/Liams-theCreator",
      "commits": 196,
      "avatar": "https://avatars.githubusercontent.com/u/40075202?u=701343b9bdf414c24ff7fd250b845ede64ce3f3c&v=4&s=40"
    },
    {
      "rank": 174,
      "username": "ZakariaAyad1",
      "realname": "Zakaria AYAD",
      "profile": "https://github.com/ZakariaAyad1",
      "commits": 192,
      "avatar": "https://avatars.githubusercontent.com/u/153334151?u=aef534675b1a2ad228a6038c0fa3c127941ef90d&v=4&s=40"
    },
    {
      "rank": 175,
      "username": "OthmanSALAHI",
      "realname": "Othman Salahi",
      "profile": "https://github.com/OthmanSALAHI",
      "commits": 189,
      "avatar": "https://avatars.githubusercontent.com/u/132019758?u=0bcb667bf3200f0e64b9b140bbb8e5b7d92a0b5a&v=4&s=40"
    },
    {
      "rank": 176,
      "username": "Anas-Magane",
      "realname": "Anas Magane",
      "profile": "https://github.com/Anas-Magane",
      "commits": 188,
      "avatar": "https://avatars.githubusercontent.com/u/127954243?u=ef7ac973b7c58f8ae9c5adb7da921fd07852d58d&v=4&s=40"
    },
    {
      "rank": 177,
      "username": "Eymeee",
      "realname": "SALHI Aymane",
      "profile": "https://github.com/Eymeee",
      "commits": 185,
      "avatar": "https://avatars.githubusercontent.com/u/195801030?u=0c355f03a31117de4cd69dbe58cfa0e40390c8e8&v=4&s=40"
    },
    {
      "rank": 178,
      "username": "RouahImad",
      "realname": "Imad Rouah",
      "profile": "https://github.com/RouahImad",
      "commits": 185,
      "avatar": "https://avatars.githubusercontent.com/u/112584755?u=474a077dc7a4ef16717f80c2a5d2b784f9d93a61&v=4&s=40"
    },
    {
      "rank": 179,
      "username": "MohaElbadry",
      "realname": "mohammed el badry",
      "profile": "https://github.com/MohaElbadry",
      "commits": 180,
      "avatar": "https://avatars.githubusercontent.com/u/92531732?u=504fc985a89492298d02fec91b7559592be94694&v=4&s=40"
    },
    {
      "rank": 180,
      "username": "0xPacman",
      "realname": "Ahmed Jadani",
      "profile": "https://github.com/0xPacman",
      "commits": 179,
      "avatar": "https://avatars.githubusercontent.com/u/22503811?u=7fec569f3ad61e66bbe42268822ff7a4f4b6b0dc&v=4&s=40"
    },
    {
      "rank": 181,
      "username": "anass-asbai",
      "realname": "anasbai",
      "profile": "https://github.com/anass-asbai",
      "commits": 179,
      "avatar": "https://avatars.githubusercontent.com/u/61348436?u=51b1eb9fedb575e762a60e7f51e0c865e8dfde42&v=4&s=40"
    },
    {
      "rank": 182,
      "username": "yassine-khadiri",
      "realname": "Samer_V1",
      "profile": "https://github.com/yassine-khadiri",
      "commits": 174,
      "avatar": "https://avatars.githubusercontent.com/u/77007791?u=5a26067b37aa611c027f988cc557f2e9b104ab61&v=4&s=40"
    },
    {
      "rank": 183,
      "username": "nouredinateur",
      "realname": "NOUR-EDDINE NAFZAOUI",
      "profile": "https://github.com/nouredinateur",
      "commits": 173,
      "avatar": "https://avatars.githubusercontent.com/u/57252670?u=f9b70f84aa06c461fbf89ba82b1a199a79605437&v=4&s=40"
    },
    {
      "rank": 184,
      "username": "ilyassatlassi",
      "realname": "ilyass atlassi",
      "profile": "https://github.com/ilyassatlassi",
      "commits": 173,
      "avatar": "https://avatars.githubusercontent.com/u/92442582?u=477fdcb2c51945509ac0a7d8fa827d39912cc519&v=4&s=40"
    },
    {
      "rank": 185,
      "username": "anyantudre",
      "realname": "Alban NYANTUDRE",
      "profile": "https://github.com/anyantudre",
      "commits": 170,
      "avatar": "https://avatars.githubusercontent.com/u/121746248?u=4000822a25e7adfad2df513f67f9cd599dacb4a0&v=4&s=40"
    },
    {
      "rank": 186,
      "username": "khsellami",
      "realname": "khadija sellami",
      "profile": "https://github.com/khsellami",
      "commits": 170,
      "avatar": "https://avatars.githubusercontent.com/u/152222105?v=4&s=40"
    },
    {
      "rank": 187,
      "username": "rosiepiee",
      "realname": "★ ashy boy ★",
      "profile": "https://github.com/rosiepiee",
      "commits": 168,
      "avatar": "https://avatars.githubusercontent.com/u/212720657?u=1bdcb00f313ee105e94db5544213b370384a05fb&v=4&s=40"
    },
    {
      "rank": 188,
      "username": "HoussamMrabet",
      "realname": "Houssam Mrabet",
      "profile": "https://github.com/HoussamMrabet",
      "commits": 167,
      "avatar": "https://avatars.githubusercontent.com/u/52783782?u=4cd352932175e1ba4a08a093c7f8dd22c341085c&v=4&s=40"
    },
    {
      "rank": 189,
      "username": "UnesseAh",
      "realname": "Youness AHASLA",
      "profile": "https://github.com/UnesseAh",
      "commits": 166,
      "avatar": "https://avatars.githubusercontent.com/u/48359259?u=3d2f96d9a4c2acbc085e03f06989888473e80d6f&v=4&s=40"
    },
    {
      "rank": 190,
      "username": "najzdev",
      "realname": "Hamza Labbaalli",
      "profile": "https://github.com/najzdev",
      "commits": 162,
      "avatar": "https://avatars.githubusercontent.com/u/114623203?u=adfecb3a60e527f718dbc6ececad6d1cfca036db&v=4&s=40"
    },
    {
      "rank": 191,
      "username": "Douaa1819",
      "realname": "Douaa1920",
      "profile": "https://github.com/Douaa1819",
      "commits": 161,
      "avatar": "https://avatars.githubusercontent.com/u/125483549?u=7cf5933fb7bbbc1c499588e113808a95e3bc17b5&v=4&s=40"
    },
    {
      "rank": 192,
      "username": "yelouafi",
      "realname": "Yassine Elouafi",
      "profile": "https://github.com/yelouafi",
      "commits": 161,
      "avatar": "https://avatars.githubusercontent.com/u/5453835?u=2c94e59e321a57a0202cff5e9605611ced33db4f&v=4&s=40"
    },
    {
      "rank": 193,
      "username": "zakaria-chahboun",
      "realname": "zakaria chahboun",
      "profile": "https://github.com/zakaria-chahboun",
      "commits": 160,
      "avatar": "https://avatars.githubusercontent.com/u/18173275?u=911dd2416edfbf1b78ecb3c8f777e2e0885dc430&v=4&s=40"
    },
    {
      "rank": 194,
      "username": "YounesMoukhlij",
      "realname": "Younes Moukhlij",
      "profile": "https://github.com/YounesMoukhlij",
      "commits": 160,
      "avatar": "https://avatars.githubusercontent.com/u/123767564?u=d30bb7878dd1efb59824c847c9a833411193de42&v=4&s=40"
    },
    {
      "rank": 195,
      "username": "aka1976mb",
      "realname": "MUSTAPHA BARKI",
      "profile": "https://github.com/aka1976mb",
      "commits": 159,
      "avatar": "https://avatars.githubusercontent.com/u/244008467?u=37529788efef3fd1d040bcd04b046abbc6d8aae8&v=4&s=40"
    },
    {
      "rank": 196,
      "username": "black-purple",
      "realname": "Abderrahman DAKIR ALLAH",
      "profile": "https://github.com/black-purple",
      "commits": 159,
      "avatar": "https://avatars.githubusercontent.com/u/82895430?u=bc753d78d92d95006bcd5975c0b106a794c0e3af&v=4&s=40"
    },
    {
      "rank": 197,
      "username": "AadelAferyad",
      "realname": "AadelAferyad",
      "profile": "https://github.com/AadelAferyad",
      "commits": 157,
      "avatar": "https://avatars.githubusercontent.com/u/61366826?u=18b99d0b5b801bef658e10103fc6a9b49dbb4dd7&v=4&s=40"
    },
    {
      "rank": 198,
      "username": "Matsadura",
      "realname": "Zidane ZAOUI",
      "profile": "https://github.com/Matsadura",
      "commits": 157,
      "avatar": "https://avatars.githubusercontent.com/u/132571698?u=c6415b41d76941474cfe0d7723a6c42d3bd8eac3&v=4&s=40"
    },
    {
      "rank": 199,
      "username": "anassk01",
      "realname": "anassk",
      "profile": "https://github.com/anassk01",
      "commits": 156,
      "avatar": "https://avatars.githubusercontent.com/u/16940778?u=a8e0367e43bbb2a64b92abab01011822b3a25950&v=4&s=40"
    },
    {
      "rank": 200,
      "username": "aka76bm",
      "realname": "MUSTAPHA BARKI",
      "profile": "https://github.com/aka76bm",
      "commits": 155,
      "avatar": "https://avatars.githubusercontent.com/u/233129553?u=41c94fb7aac678455de7c8a233bacac482d03c57&v=4&s=40"
    },
    {
      "rank": 201,
      "username": "Iduoad",
      "realname": "Mohammed Daoudi",
      "profile": "https://github.com/Iduoad",
      "commits": 154,
      "avatar": "https://avatars.githubusercontent.com/u/25715906?u=9bc6e4247dc73463b619e996af5106ba287b1e86&v=4&s=40"
    },
    {
      "rank": 202,
      "username": "Medamine-Bahassou",
      "realname": "Mohamed Amine BAHASSOU",
      "profile": "https://github.com/Medamine-Bahassou",
      "commits": 153,
      "avatar": "https://avatars.githubusercontent.com/u/146652318?u=c9e5879aa821d5f391f7507c1b2b9884510a9484&v=4&s=40"
    },
    {
      "rank": 203,
      "username": "saidMounaim",
      "realname": "Said Mounaim",
      "profile": "https://github.com/saidMounaim",
      "commits": 151,
      "avatar": "https://avatars.githubusercontent.com/u/25122031?u=597deadda9e30c6e55b2bd78fc7968bde77f7df3&v=4&s=40"
    },
    {
      "rank": 204,
      "username": "AyoubBellaoui",
      "realname": "Ayoub Bellaoui",
      "profile": "https://github.com/AyoubBellaoui",
      "commits": 151,
      "avatar": "https://avatars.githubusercontent.com/u/89253085?u=03eb9218257cea2b69e011ddaed5dfcaa1117786&v=4&s=40"
    },
    {
      "rank": 205,
      "username": "jezozs",
      "realname": "Mohamed Badr El Wardi",
      "profile": "https://github.com/jezozs",
      "commits": 150,
      "avatar": "https://avatars.githubusercontent.com/u/149475597?u=6044cf0d13c3bf4d4d49ea4e6448b899737b85aa&v=4&s=40"
    },
    {
      "rank": 206,
      "username": "abdoachhoubi",
      "realname": "Astro",
      "profile": "https://github.com/abdoachhoubi",
      "commits": 145,
      "avatar": "https://avatars.githubusercontent.com/u/78739445?u=f989f1ec8a425bc8f6bf18adb6f9708396f04a56&v=4&s=40"
    },
    {
      "rank": 207,
      "username": "C-EB",
      "realname": "Charif El Belghiti",
      "profile": "https://github.com/C-EB",
      "commits": 145,
      "avatar": "https://avatars.githubusercontent.com/u/95632523?u=47325ce4cad97a39b2e0748d609e5abd33506d1a&v=4&s=40"
    },
    {
      "rank": 208,
      "username": "M97Chahboun",
      "realname": "Mohammed  CHAHBOUN",
      "profile": "https://github.com/M97Chahboun",
      "commits": 144,
      "avatar": "https://avatars.githubusercontent.com/u/69054810?u=1604262ad7e40d79b2f520fe13a690a14c9718ab&v=4&s=40"
    },
    {
      "rank": 209,
      "username": "younes-dro",
      "realname": "Senior WordPress & React developer",
      "profile": "https://github.com/younes-dro",
      "commits": 142,
      "avatar": "https://avatars.githubusercontent.com/u/31171?u=18bf4c0065c1458850df58ab0504f3299d85d3b2&v=4&s=40"
    },
    {
      "rank": 210,
      "username": "HMSTR63",
      "realname": "HMSTRX",
      "profile": "https://github.com/HMSTR63",
      "commits": 142,
      "avatar": "https://avatars.githubusercontent.com/u/122762403?u=e945bc1fcc85cc0dc1230394d69192255ea7b662&v=4&s=40"
    },
    {
      "rank": 211,
      "username": "ayoubm11",
      "realname": "Ayoub MOURADI",
      "profile": "https://github.com/ayoubm11",
      "commits": 140,
      "avatar": "https://avatars.githubusercontent.com/u/125606567?u=1074bc0d1a145a2fc3514cb717ae376d9f6b17cc&v=4&s=40"
    },
    {
      "rank": 212,
      "username": "IbLahlou",
      "realname": "Lahlou ibrahim",
      "profile": "https://github.com/IbLahlou",
      "commits": 139,
      "avatar": "https://avatars.githubusercontent.com/u/105231126?u=8288082576eeda1dec1c638e1247e116c5a4d24f&v=4&s=40"
    },
    {
      "rank": 213,
      "username": "youssef-bahida",
      "realname": "YOUSSEF BAHIDA",
      "profile": "https://github.com/youssef-bahida",
      "commits": 139,
      "avatar": "https://avatars.githubusercontent.com/u/240362454?u=f21bc50353c21f1e1f7bebb211a422c9b78c4f85&v=4&s=40"
    },
    {
      "rank": 214,
      "username": "ezakariaa",
      "realname": "Zakaria ELORCHE",
      "profile": "https://github.com/ezakariaa",
      "commits": 139,
      "avatar": "https://avatars.githubusercontent.com/u/135072807?u=71ab47e2b62b5c028472f2788d10ca8a09e7d26b&v=4&s=40"
    },
    {
      "rank": 215,
      "username": "Ismailco",
      "realname": "ismail courr",
      "profile": "https://github.com/Ismailco",
      "commits": 138,
      "avatar": "https://avatars.githubusercontent.com/u/25227022?u=bfd24a9e3d23519f4e0b395e282d88ce8b46d0b6&v=4&s=40"
    },
    {
      "rank": 216,
      "username": "ayoub22222222",
      "realname": "MOHAMMED AYOUB ESSBAI",
      "profile": "https://github.com/ayoub22222222",
      "commits": 137,
      "avatar": "https://avatars.githubusercontent.com/u/79339502?u=cd5f71d8dc5dbdbd44140a22496f6e495a631124&v=4&s=40"
    },
    {
      "rank": 217,
      "username": "SilentSarah",
      "realname": "Hicham S.Meftah",
      "profile": "https://github.com/SilentSarah",
      "commits": 135,
      "avatar": "https://avatars.githubusercontent.com/u/104469649?u=a19c3b6547a1b1214b341f2202f9d59cbb402393&v=4&s=40"
    },
    {
      "rank": 218,
      "username": "yoesefab",
      "realname": "Youssef Abou Eljihad",
      "profile": "https://github.com/yoesefab",
      "commits": 134,
      "avatar": "https://avatars.githubusercontent.com/u/82283823?u=038a9fba581f344409fb98b34aee370a898f2eae&v=4&s=40"
    },
    {
      "rank": 219,
      "username": "NawfalMotii79",
      "profile": "https://github.com/NawfalMotii79",
      "commits": 134,
      "avatar": "https://avatars.githubusercontent.com/u/215612484?v=4&s=40"
    },
    {
      "rank": 220,
      "username": "thefledgedhurricane",
      "realname": "ihababdelbasset annaki",
      "profile": "https://github.com/thefledgedhurricane",
      "commits": 132,
      "avatar": "https://avatars.githubusercontent.com/u/55835529?u=46d8733fde48213211f3e1418c6af4b16e81a254&v=4&s=40"
    },
    {
      "rank": 221,
      "username": "Wiran-Larbi",
      "realname": "DotCipher",
      "profile": "https://github.com/Wiran-Larbi",
      "commits": 131,
      "avatar": "https://avatars.githubusercontent.com/u/71338128?u=0d238b3d6522e2ddd73fb1dd20c1da695359d347&v=4&s=40"
    },
    {
      "rank": 222,
      "username": "yismaili",
      "realname": "younes ismaili",
      "profile": "https://github.com/yismaili",
      "commits": 131,
      "avatar": "https://avatars.githubusercontent.com/u/69278312?u=9d685836ea005804cef8fc69ca401acd2682f87e&v=4&s=40"
    },
    {
      "rank": 223,
      "username": "48d31kh413k",
      "profile": "https://github.com/48d31kh413k",
      "commits": 130,
      "avatar": "https://avatars.githubusercontent.com/u/65833007?u=9be65d007cd7391e8ba5e099e47644a3aa9d918e&v=4&s=40"
    },
    {
      "rank": 224,
      "username": "Madani00",
      "realname": "010101",
      "profile": "https://github.com/Madani00",
      "commits": 128,
      "avatar": "https://avatars.githubusercontent.com/u/123333191?u=cd54301cdc19a0d4bd4412da300a8ed9f5e65cbb&v=4&s=40"
    },
    {
      "rank": 225,
      "username": "amyaby",
      "realname": "Amy aby",
      "profile": "https://github.com/amyaby",
      "commits": 127,
      "avatar": "https://avatars.githubusercontent.com/u/113394974?u=8eee2002d44300f455e0a405b123ac9e5403d797&v=4&s=40"
    },
    {
      "rank": 226,
      "username": "yassinerahhou",
      "realname": "yassine rahhou",
      "profile": "https://github.com/yassinerahhou",
      "commits": 126,
      "avatar": "https://avatars.githubusercontent.com/u/125989457?u=d419df3710e903d2c71f6a0d9e94205a239b3766&v=4&s=40"
    },
    {
      "rank": 227,
      "username": "ayoubedd",
      "realname": "Ayoub Eddaoudi",
      "profile": "https://github.com/ayoubedd",
      "commits": 125,
      "avatar": "https://avatars.githubusercontent.com/u/59961489?u=0ebf452e175202f8466228757f4cbe20bff12a40&v=4&s=40"
    },
    {
      "rank": 228,
      "username": "BrahimChatri",
      "realname": "Brahim Chatri",
      "profile": "https://github.com/BrahimChatri",
      "commits": 123,
      "avatar": "https://avatars.githubusercontent.com/u/86537137?u=0986e8ff3b33cf2a2abb1cbc88caf7cdbfb427ae&v=4&s=40"
    },
    {
      "rank": 229,
      "username": "xAyBix",
      "realname": "Akram BELBEKRI",
      "profile": "https://github.com/xAyBix",
      "commits": 123,
      "avatar": "https://avatars.githubusercontent.com/u/123202881?u=7de234cb44adfef0bf7934046f665c81e5b6ffa2&v=4&s=40"
    },
    {
      "rank": 230,
      "username": "makarkao",
      "realname": "makarkao",
      "profile": "https://github.com/makarkao",
      "commits": 123,
      "avatar": "https://avatars.githubusercontent.com/u/179608856?u=18de1596f198ee75e5fe387c4e61583522ab0b44&v=4&s=40"
    },
    {
      "rank": 231,
      "username": "exoks",
      "realname": "Oussama Ezzaou",
      "profile": "https://github.com/exoks",
      "commits": 123,
      "avatar": "https://avatars.githubusercontent.com/u/100782869?u=babd368a61d76b02e3cde68759fd58d3c44d4fb5&v=4&s=40"
    },
    {
      "rank": 232,
      "username": "Wayde-Ouadie",
      "realname": "Ouadie El Fengour",
      "profile": "https://github.com/Wayde-Ouadie",
      "commits": 122,
      "avatar": "https://avatars.githubusercontent.com/u/91639455?u=1da08fa2defa517fe0c2aa6b885bd3fa71736a18&v=4&s=40"
    },
    {
      "rank": 233,
      "username": "anassBelcaid",
      "realname": "anass",
      "profile": "https://github.com/anassBelcaid",
      "commits": 121,
      "avatar": "https://avatars.githubusercontent.com/u/1475886?u=6845edb826265a71bb40fe4e9b388acb80b77405&v=4&s=40"
    },
    {
      "rank": 234,
      "username": "Abdogouhmad",
      "realname": "Result<T>",
      "profile": "https://github.com/Abdogouhmad",
      "commits": 120,
      "avatar": "https://avatars.githubusercontent.com/u/107504577?u=fa7826cce01195c9679edfb1ff92e19b8a3668f9&v=4&s=40"
    },
    {
      "rank": 235,
      "username": "yhaddar",
      "realname": "youssef haddar",
      "profile": "https://github.com/yhaddar",
      "commits": 120,
      "avatar": "https://avatars.githubusercontent.com/u/88948270?u=2a7146b8dd1260138c1061c77feefea618798690&v=4&s=40"
    },
    {
      "rank": 236,
      "username": "AhmedCoolProjects",
      "realname": "Ahmed Cool Projects",
      "profile": "https://github.com/AhmedCoolProjects",
      "commits": 119,
      "avatar": "https://avatars.githubusercontent.com/u/72823374?u=42ac823891b92a8af81ae245eb2bee4d512c9dfa&v=4&s=40"
    },
    {
      "rank": 237,
      "username": "taher-el-mehdi",
      "realname": "TAHER El Mehdi",
      "profile": "https://github.com/taher-el-mehdi",
      "commits": 119,
      "avatar": "https://avatars.githubusercontent.com/u/57680648?u=569a0a1db853968c95034d5e80e1a30fe368f9d5&v=4&s=40"
    },
    {
      "rank": 238,
      "username": "ABDE-LKADER",
      "realname": "Abdelkader ADOUAB",
      "profile": "https://github.com/ABDE-LKADER",
      "commits": 117,
      "avatar": "https://avatars.githubusercontent.com/u/82539204?u=c4bf84d4229b24d0bf4f50635f73b6aa193bffa6&v=4&s=40"
    },
    {
      "rank": 239,
      "username": "DexterTaha",
      "realname": "TAIDI LAAMIRI Taha",
      "profile": "https://github.com/DexterTaha",
      "commits": 115,
      "avatar": "https://avatars.githubusercontent.com/u/130682580?u=390785c095952bceb0e39a679bc41a0ddd07f081&v=4&s=40"
    },
    {
      "rank": 240,
      "username": "mohammedaassou",
      "realname": "Mohamed Aassou",
      "profile": "https://github.com/mohammedaassou",
      "commits": 115,
      "avatar": "https://avatars.githubusercontent.com/u/168199486?u=40043490784d2a22e5bc220ccbb8979cb0a8bcc8&v=4&s=40"
    },
    {
      "rank": 241,
      "username": "ANOUAR00-1",
      "realname": "ANOUAR BENTAHAR",
      "profile": "https://github.com/ANOUAR00-1",
      "commits": 113,
      "avatar": "https://avatars.githubusercontent.com/u/205829273?u=234a9693af7702915e6da3e07171e6f32ff96243&v=4&s=40"
    },
    {
      "rank": 242,
      "username": "khzouhair",
      "realname": "Khadija Zouhair",
      "profile": "https://github.com/khzouhair",
      "commits": 112,
      "avatar": "https://avatars.githubusercontent.com/u/147002128?u=0e8ac4c89f9aef4c2a17a1ed3d2e4aadee40a3c5&v=4&s=40"
    },
    {
      "rank": 243,
      "username": "saadazghour",
      "realname": "Saad Azghour",
      "profile": "https://github.com/saadazghour",
      "commits": 112,
      "avatar": "https://avatars.githubusercontent.com/u/33766249?u=25e237db7a634ad595ce5e224e5b59424d34a076&v=4&s=40"
    },
    {
      "rank": 244,
      "username": "amilemia",
      "realname": "Amilemia",
      "profile": "https://github.com/amilemia",
      "commits": 112,
      "avatar": "https://avatars.githubusercontent.com/u/125489574?u=6f373fc4447e06636174ae5b89f9fdb3668923ad&v=4&s=40"
    },
    {
      "rank": 245,
      "username": "0xShady",
      "realname": "Achraf El fadili",
      "profile": "https://github.com/0xShady",
      "commits": 111,
      "avatar": "https://avatars.githubusercontent.com/u/58003696?u=4633211ff6e8ed07557efb1fa47a5d35ad1683ff&v=4&s=40"
    },
    {
      "rank": 246,
      "username": "zachary013",
      "realname": "Zakariae Azarkan",
      "profile": "https://github.com/zachary013",
      "commits": 111,
      "avatar": "https://avatars.githubusercontent.com/u/147554555?u=02aec5e9d58beb894a80ce2bc4bcb75d114be418&v=4&s=40"
    },
    {
      "rank": 247,
      "username": "aouchcha",
      "realname": "Achraf OUCHCHATE",
      "profile": "https://github.com/aouchcha",
      "commits": 111,
      "avatar": "https://avatars.githubusercontent.com/u/135086495?u=020ea8e712b5c50c8480ccd2bc668902781379d7&v=4&s=40"
    },
    {
      "rank": 248,
      "username": "Toowan0x1",
      "realname": "Omar",
      "profile": "https://github.com/Toowan0x1",
      "commits": 107,
      "avatar": "https://avatars.githubusercontent.com/u/50034094?u=f8f25f0e94296966cce41237bfa93178704fa4bb&v=4&s=40"
    },
    {
      "rank": 249,
      "username": "0xhoussam",
      "realname": "houssam",
      "profile": "https://github.com/0xhoussam",
      "commits": 106,
      "avatar": "https://avatars.githubusercontent.com/u/32068899?u=f930c98226419e56198da33b957551184bd18f4f&v=4&s=40"
    },
    {
      "rank": 250,
      "username": "ziko54545",
      "realname": "Zakaria  Hannane",
      "profile": "https://github.com/ziko54545",
      "commits": 105,
      "avatar": "https://avatars.githubusercontent.com/u/173511569?u=cfd688dd4812786c8890da1971dc1214afa69b71&v=4&s=40"
    },
    {
      "rank": 251,
      "username": "azedineouhadou",
      "realname": "Azedine Ouhadou",
      "profile": "https://github.com/azedineouhadou",
      "commits": 105,
      "avatar": "https://avatars.githubusercontent.com/u/45069518?u=b3393fe0a1d7b76aada9811db890ec25dade023e&v=4&s=40"
    },
    {
      "rank": 252,
      "username": "devloopcode",
      "realname": "IDBENOUAKRIM Mohamed",
      "profile": "https://github.com/devloopcode",
      "commits": 105,
      "avatar": "https://avatars.githubusercontent.com/u/74541189?u=ce5accb92ead075b9470c1775621c90ee72a3400&v=4&s=40"
    },
    {
      "rank": 253,
      "username": "drisskhattabi6",
      "realname": "Idriss Khattabi",
      "profile": "https://github.com/drisskhattabi6",
      "commits": 104,
      "avatar": "https://avatars.githubusercontent.com/u/49597702?u=61693c03fce09ade59767bce4c30d6d3c5fa20e3&v=4&s=40"
    },
    {
      "rank": 254,
      "username": "mooka007",
      "realname": "Mooka",
      "profile": "https://github.com/mooka007",
      "commits": 104,
      "avatar": "https://avatars.githubusercontent.com/u/47282413?u=7d1460e12bf6bc9306b913df48041ed9bd0d971f&v=4&s=40"
    },
    {
      "rank": 255,
      "username": "ImadIdaliouali",
      "realname": "Imad IDALI OUALI",
      "profile": "https://github.com/ImadIdaliouali",
      "commits": 103,
      "avatar": "https://avatars.githubusercontent.com/u/96796912?u=e29523a147850af0d70198bfb3236cc5ec3ab1dd&v=4&s=40"
    },
    {
      "rank": 256,
      "username": "abouabba",
      "realname": "bouabbadi abdessamad",
      "profile": "https://github.com/abouabba",
      "commits": 102,
      "avatar": "https://avatars.githubusercontent.com/u/173314568?u=fb6273531fbac774f9e8a10ba35700188f8d8a7a&v=4&s=40"
    }
  ]
}
